Workbook

Sheet BD_Clez_Premigracion
A1: # de documento | B1: Afiliado | C1: Cedula | D1: DirecciÃ³n | E1: Telefono | F1: Email | G1: Valor | H1: Sucursal | I1: Plan / Producto | J1: Canal | K1: Fuente | L1: Medio | M1: CampaÃ±a | N1: Estado | O1: Forma de Pago | P1: Fecha | Q1: Cedula usuario que registro | R1: Usuario que registro | S1: Entrenador | T1: Usuario que suplanta | U1: Tipo | V1: Motivo | W1: Observaciones Documento | X1: Â¿Tuvo cortesia? | Y1: GestiÃ³n CRM | Z1: Tipo Afiliado | AA1: FacturaciÃ³n electronica | AB1: Firmada | AC1: Se encentra en FP+
A2: FPF-33558 | B2: LAURIN VANESSA MONTAÂ¥O SANTIAGO | C2: 1091652989 | D2: cra 19 17 - 65 | E2: 3115583628 | F2: laurinsvanesa31@gmail.com | G2: 89 | H2: Boulevard | I2: PLAN DEBITO AUTOMÃ¡TICO POR 89.000 (PERMANENCIA 12 MESES) | J2: On Line | N2: Activo | O2: PAGOS ON LINE / CLEZ PAY-89000.00 | P2: 45946.764 | Q2: 7777777 | R2: CLEZ | U2: Factura de Venta | W2: Facturado automaticamente por CLEZ PAY Facturado automaticamente por CLEZ PAY | X2: No | Y2: Si | Z2: Renovado | AA2: No enviada | AB2: No | AC2: =IFERROR(VLOOKUP(C2,MigradosEfectivamente!B:B,1,FALSE),"No encontrado") -> No encontrado
A3: FP-34356 | B3: JUAN FERNANDO ARAUJO LAZCANO | C3: 1050918470 | D3: PROVENZA | E3: 3243181439 | F3: jaraujolazcano@gmail.com | G3: 89 | H3: Provenza | I3: PLAN DEBITO AUTOMÃ¡TICO POR 89.000 (PERMANENCIA 12 MESES) | J3: On Line | N3: Activo | O3: PAGOS ON LINE / CLEZ PAY-89000.00 | P3: 45946.713 | Q3: 7777777 | R3: CLEZ | U3: Factura de Venta | W3: Facturado automaticamente por CLEZ PAY Facturado automaticamente por CLEZ PAY | X3: No | Y3: Si | Z3: Renovado | AA3: Enviada | AB3: No | AC3: =IFERROR(VLOOKUP(C3,MigradosEfectivamente!B:B,1,FALSE),"No encontrado") -> No encontrado
A4: FC-65942 | B4: VALENTINA SAVEDRA HOYOS | C4: 1030542921 | D4: Calle 64#2w76 Mutis | E4: 3196218540 | F4: valentinahoyos77@gmail.com | G4: 89 | H4: Ciudadela | I4: PLAN DEBITO AUTOMÃ¡TICO POR 89.000 (PERMANENCIA 12 MESES) | J4: On Line | N4: Activo | O4: PAGOS ON LINE / CLEZ PAY-89000.00 | P4: 45946.683 | Q4: 7777777 | R4: CLEZ | U4: Factura de Venta | W4: Facturado automaticamente por CLEZ PAY Facturado automaticamente por CLEZ PAY | X4: Si | Y4: Si | Z4: Renovado | AA4: Enviada | AB4: No | AC4: =IFERROR(VLOOKUP(C4,MigradosEfectivamente!B:B,1,FALSE),"No encontrado") -> 1030542921
A5: FPP-26926 | B5: ASURY ALEJANDRA RENOGA RENOGA | C5: 1004823152 | D5: PIEDECUESTA | E5: 3224708688 | F5: pa318344@gmail.com | G5: 89 | H5: Piedecuesta | I5: PLAN DEBITO AUTOMÃ¡TICO POR 89.000 (PERMANENCIA 12 MESES) | J5: On Line | N5: Activo | O5: PAGOS ON LINE / CLEZ PAY-89000.00 | P5: 45945.586 | Q5: 7777777 | R5: CLEZ | U5: Factura de Venta | W5: Facturado automaticamente por CLEZ PAY (Cron cobro suscripcion) Facturado automaticamente por CLEZ PAY (Cron cobro suscripcion) | X5: No | Y5: Si | Z5: Renovado | AA5: No enviada | AB5: No | AC5: =IFERROR(VLOOKUP(C5,MigradosEfectivamente!B:B,1,FALSE),"No encontrado") -> No encontrado
A6: FP-34329 | B6: LILIAM MAYERLIS CABRERA ARAUJO | C6: 1002295958 | D6: PROVENZA | E6: 57 301 4934088 | F6: Cabreraaraujo2003@gmail.com | G6: 89 | H6: Provenza | I6: PLAN DEBITO AUTOMÃ¡TICO POR 89.000 (PERMANENCIA 12 MESES) | J6: On Line | N6: Activo | O6: PAGOS ON LINE / CLEZ PAY-89000.00 | P6: 45944.486 | Q6: 7777777 | R6: CLEZ | U6: Factura de Venta | W6: Facturado automaticamente por CLEZ PAY Facturado automaticamente por CLEZ PAY | X6: No | Y6: Si | Z6: Renovado | AA6: No enviada | AB6: No | AC6: =IFERROR(VLOOKUP(C6,MigradosEfectivamente!B:B,1,FALSE),"No encontrado") -> No encontrado
A7: CE-12471 | B7: ALEJANDRA RAMÃREZ | C7: 1092349320 | D7: Calle 11 an 11 ae 68 conjunto torres del centenario, torre Santander apto 802 | E7: 3132352718 | F7: ramirezalejandra56@gmail.com | G7: 89 | H7: Ceiba | I7: PLAN DEBITO AUTOMÃ¡TICO POR 89.000 (PERMANENCIA 12 MESES) | J7: On Line | N7: Activo | O7: PAGOS ON LINE / CLEZ PAY-89000.00 | P7: 45940.585 | Q7: 7777777 | R7: CLEZ | U7: Factura de Venta | W7: Facturado automaticamente por CLEZ PAY (Cron cobro suscripcion) Facturado automaticamente por CLEZ PAY (Cron cobro suscripcion) | X7: No | Y7: Si | Z7: Nuevo | AA7: Enviada | AB7: No | AC7: =IFERROR(VLOOKUP(C7,MigradosEfectivamente!B:B,1,FALSE),"No encontrado") -> No encontrado
A8: FP-34313 | B8: ZORELISA FIGUEROA SAAVEDRA | C8: 1050918718 | D8: PROVENZA | E8: 3128293091 | F8: zorelisafigueroa1705@gmail.com | G8: 89 | H8: Provenza | I8: PLAN DEBITO AUTOMÃ¡TICO POR 89.000 (PERMANENCIA 12 MESES) | J8: On Line | N8: Activo | O8: PAGOS ON LINE / CLEZ PAY-89000.00 | P8: 45940.49 | Q8: 7777777 | R8: CLEZ | U8: Factura de Venta | W8: Facturado automaticamente por CLEZ PAY Facturado automaticamente por CLEZ PAY | X8: No | Y8: Si | Z8: Renovado | AA8: Enviada | AB8: No | AC8: =IFERROR(VLOOKUP(C8,MigradosEfectivamente!B:B,1,FALSE),"No encontrado") -> No encontrado
A9: FP-34310 | B9: DANIEL RODRIGUEZ | C9: 1142716057 | D9: Av 87 #20-134 | E9: 3205124628 | F9: sandoval.rodriguez.danielsn@gmail.com | G9: 89 | H9: Provenza | I9: PLAN DEBITO AUTOMÃ¡TICO POR 89.000 (PERMANENCIA 12 MESES) | J9: On Line | N9: Activo | O9: PAGOS ON LINE / CLEZ PAY-89000.00 | P9: 45940.338 | Q9: 7777777 | R9: CLEZ | U9: Factura de Venta | W9: Facturado automaticamente por CLEZ PAY (Cron cobro suscripcion) Facturado automaticamente por CLEZ PAY (Cron cobro suscripcion) | X9: No | Y9: Si | Z9: Renovado | AA9: Enviada | AB9: No | AC9: =IFERROR(VLOOKUP(C9,MigradosEfectivamente!B:B,1,FALSE),"No encontrado") -> No encontrado
A10: CE-12464 | B10: YEISON ALEXANDER PEDRAZA ARDILA | C10: 1005025225 | D10: cucuta | E10: 3022747153 | F10: PEDRAZA1134@GMAIL.COM | G10: 99 | H10: Ceiba | I10: PLAN DEBITO AUTOMÃ¡TICO POR 99.000 (PERMANENCIA 12 MESES) | J10: On Line | N10: Activo | O10: PAGOS ON LINE / CLEZ PAY-99000.00 | P10: 45940.337 | Q10: 7777777 | R10: CLEZ | U10: Factura de Venta | W10: Facturado automaticamente por CLEZ PAY (Cron cobro suscripcion) Facturado automaticamente por CLEZ PAY (Cron cobro suscripcion) | X10: Si | Y10: Si | Z10: Renovado | AA10: Enviada | AB10: No | AC10: =IFERROR(VLOOKUP(C10,MigradosEfectivamente!B:B,1,FALSE),"No encontrado") -> No encontrado
A11: CE-12463 | B11: OMAR CASTELLANO | C11: 5004717783 | D11: Calle 1N #0a-24 edificio rosmar | E11: 3017550017 | F11: chitomeio@hotmail.com | G11: 99 | H11: Ceiba | I11: PLAN DEBITO AUTOMÃ¡TICO POR 99.000 (PERMANENCIA 12 MESES) | J11: On Line | N11: Activo | O11: PAGOS ON LINE / CLEZ PAY-99000.00 | P11: 45940.334 | Q11: 7777777 | R11: CLEZ | U11: Factura de Venta | W11: Facturado automaticamente por CLEZ PAY (Cron cobro suscripcion) Facturado automaticamente por CLEZ PAY (Cron cobro suscripcion) | X11: No | Y11: Si | Z11: Renovado | AA11: Enviada | AB11: No | AC11: =IFERROR(VLOOKUP(C11,MigradosEfectivamente!B:B,1,FALSE),"No encontrado") -> No encontrado
A12: FC-65883 | B12: MARIA ALEJANDRA RODRIGUEZ REYES | C12: 1098801968 | D12: SAN FRANCISCO | E12: 3186962347 | F12: marialejandrarr25@gmail.com | G12: 89 | H12: Ciudadela | I12: PLAN DEBITO AUTOMÃ¡TICO POR 89.000 (PERMANENCIA 12 MESES) | J12: On Line | N12: Activo | O12: PAGOS ON LINE / CLEZ PAY-89000.00 | P12: 45939.876 | Q12: 7777777 | R12: CLEZ | U12: Factura de Venta | W12: Facturado automaticamente por CLEZ PAY (Cron cobro suscripcion) Facturado automaticamente por CLEZ PAY (Cron cobro suscripcion) | X12: No | Y12: Si | Z12: Recuperado | AA12: Enviada | AB12: No | AC12: =IFERROR(VLOOKUP(C12,MigradosEfectivamente!B:B,1,FALSE),"No encontrado") -> No encontrado
A13: PR-1731 | B13: CARLOS SANTIAGO GARCIA BARRERA | C13: 1097093302 | D13: Calle 22 #24-65 | E13: 3184407645 | F13: casagaba33@gmail.com | G13: 89 | H13: El Prado | I13: PLAN DEBITO AUTOMÃ¡TICO POR 89.000 (PERMANENCIA 12 MESES) | J13: On Line | N13: Activo | O13: PAGOS ON LINE / CLEZ PAY-89000.00 | P13: 45939.876 | Q13: 7777777 | R13: CLEZ | U13: Factura de Venta | W13: Facturado automaticamente por CLEZ PAY (Cron cobro suscripcion) Facturado automaticamente por CLEZ PAY (Cron cobro suscripcion) | X13: No | Y13: No | Z13: Renovado | AA13: Enviada | AB13: No | AC13: =IFERROR(VLOOKUP(C13,MigradosEfectivamente!B:B,1,FALSE),"No encontrado") -> No encontrado
A14: FPP-26906 | B14: GUSTAVO DIAZ | C14: 1098724742 | D14: AVEN 10N 17-92 | E14: 3155151739 | F14: gdiaz420@unab.edu.co | G14: 89 | H14: Piedecuesta | I14: PLAN DEBITO AUTOMÃ¡TICO POR 89.000 (PERMANENCIA 12 MESES) | J14: On Line | N14: Activo | O14: PAGOS ON LINE / CLEZ PAY-89000.00 | P14: 45939.587 | Q14: 7777777 | R14: CLEZ | U14: Factura de Venta | W14: Facturado automaticamente por CLEZ PAY (Cron cobro suscripcion) Facturado automaticamente por CLEZ PAY (Cron cobro suscripcion) | X14: Si | Y14: Si | Z14: Renovado | AA14: Enviada | AB14: No | AC14: =IFERROR(VLOOKUP(C14,MigradosEfectivamente!B:B,1,FALSE),"No encontrado") -> No encontrado
A15: PR-1729 | B15: JORGE LUIS MARTINEZ MARQUEZ | C15: 1007469498 | D15: CABECERA | E15: 3013919131 | F15: jorge.luis082000@gmail.com | G15: 89 | H15: El Prado | I15: PLAN DEBITO AUTOMÃ¡TICO POR 89.000 (PERMANENCIA 12 MESES) | J15: On Line | N15: Activo | O15: PAGOS ON LINE / CLEZ PAY-89000.00 | P15: 45939.586 | Q15: 7777777 | R15: CLEZ | U15: Factura de Venta | W15: Facturado automaticamente por CLEZ PAY (Cron cobro suscripcion) Facturado automaticamente por CLEZ PAY (Cron cobro suscripcion) | X15: No | Y15: Si | Z15: Renovado | AA15: Enviada | AB15: No | AC15: =IFERROR(VLOOKUP(C15,MigradosEfectivamente!B:B,1,FALSE),"No encontrado") -> No encontrado
A16: CB-8988 | B16: BRAYAN DAVID VALBUENA GELVEZ | C16: 1005326464 | D16: cabecera | E16: 3158275763 | F16: brayanvg2002@gmail.com | G16: 99 | H16: Cabecera | I16: PLAN DEBITO AUTOMÃ¡TICO POR 99.000 (PERMANENCIA 12 MESES) | J16: On Line | N16: Activo | O16: PAGOS ON LINE / CLEZ PAY-99000.00 | P16: 45939.337 | Q16: 7777777 | R16: CLEZ | U16: Factura de Venta | W16: Facturado automaticamente por CLEZ PAY (Cron cobro suscripcion) Facturado automaticamente por CLEZ PAY (Cron cobro suscripcion) | X16: No | Y16: Si | Z16: Renovado | AA16: Enviada | AB16: No | AC16: =IFERROR(VLOOKUP(C16,MigradosEfectivamente!B:B,1,FALSE),"No encontrado") -> No encontrado
A17: CB-8987 | B17: JULIAN CAMILO GOMEZ JAIME | C17: 1098650766 | D17: CABECERA | E17: 319 4146653 | F17: juliangomezjaime@gmail.com | G17: 89 | H17: Cabecera | I17: PLAN DEBITO AUTOMÃ¡TICO POR 89.000 (PERMANENCIA 12 MESES) | J17: On Line | N17: Activo | O17: PAGOS ON LINE / CLEZ PAY-89000.00 | P17: 45939.337 | Q17: 7777777 | R17: CLEZ | U17: Factura de Venta | W17: Facturado automaticamente por CLEZ PAY (Cron cobro suscripcion) Facturado automaticamente por CLEZ PAY (Cron cobro suscripcion) | X17: No | Y17: Si | Z17: Renovado | AA17: Enviada | AB17: No | AC17: =IFERROR(VLOOKUP(C17,MigradosEfectivamente!B:B,1,FALSE),"No encontrado") -> No encontrado
A18: CE-12451 | B18: JORGE LUIS GARCÃ‰S | C18: 72159538 | D18: Calle 4a #16-13 barrio san CristÃ³bal . Piedecuesta | E18: 3165357372 | F18: propio.35@hotmail.com | G18: 89 | H18: Ceiba | I18: PLAN DEBITO AUTOMATICO LOS PRIMER 3 MESES $49.900 DESDE EL CUARTO MES 89.000 (PERMANENCIA 12 MESES) | J18: On Line | N18: Activo | O18: PAGOS ON LINE / CLEZ PAY-89000.00 | P18: 45939.337 | Q18: 7777777 | R18: CLEZ | U18: Factura de Venta | W18: Facturado automaticamente por CLEZ PAY (Cron cobro suscripcion) Facturado automaticamente por CLEZ PAY (Cron cobro suscripcion) | X18: No | Y18: No | Z18: Renovado | AA18: Enviada | AB18: No | AC18: =IFERROR(VLOOKUP(C18,MigradosEfectivamente!B:B,1,FALSE),"No encontrado") -> No encontrado
A19: CB-8986 | B19: ANDREA CAROLINA REYES RODRIGUEZ | C19: 5692729 | D19: bucaramanga | E19: 3185468442 | F19: acreyesrodriguez@gmail.com | G19: 99 | H19: Cabecera | I19: PLAN DEBITO AUTOMÃ¡TICO POR 99.000 (PERMANENCIA 12 MESES) | J19: On Line | N19: Activo | O19: PAGOS ON LINE / CLEZ PAY-99000.00 | P19: 45939.334 | Q19: 7777777 | R19: CLEZ | U19: Factura de Venta | W19: Facturado automaticamente por CLEZ PAY (Cron cobro suscripcion) Facturado automaticamente por CLEZ PAY (Cron cobro suscripcion) | X19: No | Y19: Si | Z19: Renovado | AA19: Enviada | AB19: No | AC19: =IFERROR(VLOOKUP(C19,MigradosEfectivamente!B:B,1,FALSE),"No encontrado") -> No encontrado
A20: PR-1727 | B20: JOSEPH RODRIGUEZ | C20: 1098764267 | D20: Calle 36 33 44 | E20: 3177195428 | F20: josephr1326@gmail.com | G20: 89 | H20: El Prado | I20: PLAN DEBITO AUTOMÃ¡TICO POR 99.000 (PERMANENCIA 12 MESES) | J20: On Line | N20: Activo | O20: PAGOS ON LINE / CLEZ PAY-89000.00 | P20: 45939.334 | Q20: 7777777 | R20: CLEZ | U20: Factura de Venta | W20: Facturado automaticamente por CLEZ PAY (Cron cobro suscripcion) Facturado automaticamente por CLEZ PAY (Cron cobro suscripcion) | X20: No | Y20: No | Z20: Renovado | AA20: Enviada | AB20: No | AC20: =IFERROR(VLOOKUP(C20,MigradosEfectivamente!B:B,1,FALSE),"No encontrado") -> No encontrado
A21: CE-12439 | B21: JHON ANDEERSON MONTAÃ‘EZ HERNANDEZ | C21: 1091352306 | D21: calle 22an #2-110 Prados norte | E21: 3104194505 | F21: montanezjhon824@gmail.com | G21: 89 | H21: Ceiba | I21: PLAN DEBITO AUTOMÃ¡TICO POR 99.000 (PERMANENCIA 12 MESES) | J21: On Line | N21: Activo | O21: PAGOS ON LINE / CLEZ PAY-89000.00 | P21: 45938.588 | Q21: 7777777 | R21: CLEZ | U21: Factura de Venta | W21: Facturado automaticamente por CLEZ PAY (Cron cobro suscripcion) Facturado automaticamente por CLEZ PAY (Cron cobro suscripcion) | X21: Si | Y21: Si | Z21: Renovado | AA21: Enviada | AB21: No | AC21: =IFERROR(VLOOKUP(C21,MigradosEfectivamente!B:B,1,FALSE),"No encontrado") -> No encontrado
A22: FPNS-30952 | B22: TANIA ALEJANDRA BERNAL GUEVARA | C22: 1093751069 | D22: conjunto bonaire | E22: 3182330939 | F22: bernaltaniaguevara@gmail.com | G22: 349 | H22: Cucuta | I22: CLEZ 4 MESES DELUXE | J22: On Line | N22: Activo | O22: PAGOS ON LINE / CLEZ PAY-349000.00 | P22: 45938.442 | Q22: 7777777 | R22: CLEZ | U22: Factura de Venta | W22: Facturado automaticamente por CLEZ PAY Facturado automaticamente por CLEZ PAY | X22: No | Y22: Si | Z22: Recuperado | AA22: Enviada | AB22: No | AC22: =IFERROR(VLOOKUP(C22,MigradosEfectivamente!B:B,1,FALSE),"No encontrado") -> No encontrado
A23: CE-12432 | B23: MANUELA VALENTINA SERNA QUIÃ‘ONEZ | C23: 1091356063 | D23: bucaramanga | E23: 3017290615 | F23: notien@gmail.com | G23: 89 | H23: Ceiba | I23: PLAN DEBITO AUTOMÃ¡TICO POR 99.000 (PERMANENCIA 12 MESES) | J23: On Line | N23: Activo | O23: PAGOS ON LINE / CLEZ PAY-89000.00 | P23: 45938.338 | Q23: 7777777 | R23: CLEZ | U23: Factura de Venta | W23: Facturado automaticamente por CLEZ PAY (Cron cobro suscripcion) Facturado automaticamente por CLEZ PAY (Cron cobro suscripcion) | X23: No | Y23: Si | Z23: Renovado | AA23: Enviada | AB23: No | AC23: =IFERROR(VLOOKUP(C23,MigradosEfectivamente!B:B,1,FALSE),"No encontrado") -> No encontrado
A24: FPF-33461 | B24: STEPHANIE FERNANDA ARENAS RIVERA | C24: 1096702367 | D24: SAN FRANCISCO | E24: 3125072124 | F24: dprivera21@gmail.com | G24: 89 | H24: Boulevard | I24: PLAN DEBITO AUTOMÃ¡TICO POR 89.000 (PERMANENCIA 12 MESES) | J24: On Line | N24: Activo | O24: PAGOS ON LINE / CLEZ PAY-89000.00 | P24: 45938.337 | Q24: 7777777 | R24: CLEZ | U24: Factura de Venta | W24: Facturado automaticamente por CLEZ PAY (Cron cobro suscripcion) Facturado automaticamente por CLEZ PAY (Cron cobro suscripcion) | X24: No | Y24: Si | Z24: Renovado | AA24: Enviada | AB24: No | AC24: =IFERROR(VLOOKUP(C24,MigradosEfectivamente!B:B,1,FALSE),"No encontrado") -> No encontrado
A25: FPF-33460 | B25: LUIS DAVID GALVAN HERNANDEZ | C25: 1096803416 | D25: SAN FRANCISCO | E25: 3102142101 | F25: luisymarta1@gmail.com | G25: 89 | H25: Boulevard | I25: PLAN DEBITO AUTOMÃ¡TICO POR 89.000 (PERMANENCIA 12 MESES) | J25: On Line | N25: Activo | O25: PAGOS ON LINE / CLEZ PAY-89000.00 | P25: 45938.335 | Q25: 7777777 | R25: CLEZ | U25: Factura de Venta | W25: Facturado automaticamente por CLEZ PAY (Cron cobro suscripcion) Facturado automaticamente por CLEZ PAY (Cron cobro suscripcion) | X25: No | Y25: Si | Z25: Renovado | AA25: Enviada | AB25: No | AC25: =IFERROR(VLOOKUP(C25,MigradosEfectivamente!B:B,1,FALSE),"No encontrado") -> No encontrado
A26: FPNS-30950 | B26: JOSE MARIO DIAZ | C26: 1003232144 | D26: Cucuta | E26: 3007622574 | F26: Pendiente@gmail.com | G26: 99 | H26: Cucuta | I26: PLAN DEBITO AUTOMÃ¡TICO POR 99.000 (PERMANENCIA 12 MESES) | J26: On Line | N26: Activo | O26: PAGOS ON LINE / CLEZ PAY-99000.00 | P26: 45937.878 | Q26: 7777777 | R26: CLEZ | U26: Factura de Venta | W26: Facturado automaticamente por CLEZ PAY (Cron cobro suscripcion) Facturado automaticamente por CLEZ PAY (Cron cobro suscripcion) | X26: Si | Y26: Si | Z26: Renovado | AA26: No enviada | AB26: No | AC26: =IFERROR(VLOOKUP(C26,MigradosEfectivamente!B:B,1,FALSE),"No encontrado") -> No encontrado
A27: FP-34291 | B27: ALBERTO SERRANO RINCON | C27: 91269649 | D27: CRA 22 #110-31 | E27: 3013085558 | F27: YAENISERRANO@GMAIL.COM | G27: 89 | H27: Provenza | I27: PLAN DEBITO AUTOMÃ¡TICO POR 89.000 (PERMANENCIA 12 MESES) | J27: On Line | N27: Activo | O27: PAGOS ON LINE / CLEZ PAY-89000.00 | P27: 45937.773 | Q27: 7777777 | R27: CLEZ | U27: Factura de Venta | W27: Facturado automaticamente por CLEZ PAY Facturado automaticamente por CLEZ PAY | X27: No | Y27: Si | AA27: Enviada | AB27: No | AC27: =IFERROR(VLOOKUP(C27,MigradosEfectivamente!B:B,1,FALSE),"No encontrado") -> No encontrado
A28: FC-65853 | B28: ANGELA , HERNANDEZ ACEVEDO | C28: 1098791712 | D28: cll 57 7 61 | E28: 3172858734 | F28: angelahdez_29@hotmail.com | G28: 89 | H28: Ciudadela | I28: PLAN DEBITO AUTOMÃ¡TICO POR 99.000 (PERMANENCIA 12 MESES) | J28: On Line | N28: Activo | O28: PAGOS ON LINE / CLEZ PAY-89000.00 | P28: 45937.587 | Q28: 7777777 | R28: CLEZ | U28: Factura de Venta | W28: Facturado automaticamente por CLEZ PAY (Cron cobro suscripcion) Facturado automaticamente por CLEZ PAY (Cron cobro suscripcion) | X28: Si | Y28: Si | Z28: Renovado | AA28: Enviada | AB28: No | AC28: =IFERROR(VLOOKUP(C28,MigradosEfectivamente!B:B,1,FALSE),"No encontrado") -> No encontrado
A29: PR-1714 | B29: MARIA DUARTE | C29: 1101623131 | D29: Calle 33#30-35 apto 504 edificio pentagrama | E29: 3166473269 | F29: mariaalejandraduarte@gmail.com | G29: 89 | H29: El Prado | I29: PLAN DEBITO AUTOMÃ¡TICO POR 89.000 (PERMANENCIA 12 MESES) | J29: On Line | N29: Activo | O29: PAGOS ON LINE / CLEZ PAY-89000.00 | P29: 45937.586 | Q29: 7777777 | R29: CLEZ | U29: Factura de Venta | W29: Facturado automaticamente por CLEZ PAY (Cron cobro suscripcion) Facturado automaticamente por CLEZ PAY (Cron cobro suscripcion) | X29: No | Y29: Si | Z29: Nuevo | AA29: Enviada | AB29: No | AC29: =IFERROR(VLOOKUP(C29,MigradosEfectivamente!B:B,1,FALSE),"No encontrado") -> No encontrado
A30: FC-65852 | B30: KEVIN DANIEL INFANTE HERNANDEZ | C30: 1098826076 | D30: cll 59 7 61 | E30: 3012379223 | F30: kevinfante25@gmail.com | G30: 89 | H30: Ciudadela | I30: PLAN DEBITO AUTOMÃ¡TICO POR 99.000 (PERMANENCIA 12 MESES) | J30: On Line | N30: Activo | O30: PAGOS ON LINE / CLEZ PAY-89000.00 | P30: 45937.584 | Q30: 7777777 | R30: CLEZ | U30: Factura de Venta | W30: Facturado automaticamente por CLEZ PAY (Cron cobro suscripcion) Facturado automaticamente por CLEZ PAY (Cron cobro suscripcion) | X30: No | Y30: Si | Z30: Renovado | AA30: Enviada | AB30: No | AC30: =IFERROR(VLOOKUP(C30,MigradosEfectivamente!B:B,1,FALSE),"No encontrado") -> No encontrado
A31: FP-34286 | B31: SANDRA ELOINA PABON MORA | C31: 27652502 | D31: BUCARAMANGA | E31: 314 2417309 | F31: sandraeloinapm1983@gmail.com | G31: 89 | H31: Provenza | I31: PLAN DEBITO AUTOMÃ¡TICO POR 89.000 (PERMANENCIA 12 MESES) | J31: On Line | N31: Activo | O31: PAGOS ON LINE / CLEZ PAY-89000.00 | P31: 45937.444 | Q31: 7777777 | R31: CLEZ | U31: Factura de Venta | W31: Facturado automaticamente por CLEZ PAY Facturado automaticamente por CLEZ PAY | X31: No | Y31: Si | Z31: Renovado | AA31: Enviada | AB31: No | AC31: =IFERROR(VLOOKUP(C31,MigradosEfectivamente!B:B,1,FALSE),"No encontrado") -> No encontrado
A32: CB-8963 | B32: PAULA ANDREA PEÃ‘ATE NATERA | C32: 1048217134 | D32: cabecera | E32: 301 7073231 | F32: paula07andrea@hotmail.com | G32: 89 | H32: Cabecera | I32: PLAN DEBITO AUTOMÃ¡TICO POR 89.000 (PERMANENCIA 12 MESES) | J32: On Line | N32: Activo | O32: PAGOS ON LINE / CLEZ PAY-89000.00 | P32: 45937.336 | Q32: 7777777 | R32: CLEZ | U32: Factura de Venta | W32: Facturado automaticamente por CLEZ PAY (Cron cobro suscripcion) Facturado automaticamente por CLEZ PAY (Cron cobro suscripcion) | X32: No | Y32: Si | Z32: Renovado | AA32: Enviada | AB32: No | AC32: =IFERROR(VLOOKUP(C32,MigradosEfectivamente!B:B,1,FALSE),"No encontrado") -> No encontrado
A33: FPF-33444 | B33: ANGIE MONTOYA | C33: 1005261067 | D33: Carrera 41 D No.203-239 Los Andes-Floridablanca | E33: 3160447671 | F33: angiemontoyaluna02@gmail.com | G33: 89 | H33: Canaveral | I33: PLAN DEBITO AUTOMÃ¡TICO POR 89.000 (PERMANENCIA 12 MESES) | J33: On Line | N33: Activo | O33: PAGOS ON LINE / CLEZ PAY-89000.00 | P33: 45937.336 | Q33: 7777777 | R33: CLEZ | U33: Factura de Venta | W33: Facturado automaticamente por CLEZ PAY (Cron cobro suscripcion) Facturado automaticamente por CLEZ PAY (Cron cobro suscripcion) | X33: No | Y33: Si | Z33: Renovado | AA33: Enviada | AB33: No | AC33: =IFERROR(VLOOKUP(C33,MigradosEfectivamente!B:B,1,FALSE),"No encontrado") -> No encontrado
A34: CE-12406 | B34: JENNIFER SILVA | C34: 1004844070 | D34: calle 23n 4-114 prados norte | E34: 3154611341 | F34: jenifercasilva@outlook.es | G34: 99 | H34: Ceiba | I34: PLAN DEBITO AUTOMÃ¡TICO POR 99.000 (PERMANENCIA 12 MESES) | J34: On Line | N34: Activo | O34: PAGOS ON LINE / CLEZ PAY-99000.00 | P34: 45937.335 | Q34: 7777777 | R34: CLEZ | U34: Factura de Venta | W34: Facturado automaticamente por CLEZ PAY (Cron cobro suscripcion) Facturado automaticamente por CLEZ PAY (Cron cobro suscripcion) | X34: No | Y34: No | Z34: Renovado | AA34: Enviada | AB34: No | AC34: =IFERROR(VLOOKUP(C34,MigradosEfectivamente!B:B,1,FALSE),"No encontrado") -> No encontrado
A35: FPP-26893 | B35: MARIA ACOSTA | C35: 1102387884 | D35: JUNIN | E35: 3156416637 | F35: emariaacosta3572@gmail.com | G35: 89 | H35: Piedecuesta | I35: PLAN DEBITO AUTOMÃ¡TICO POR 89.000 (PERMANENCIA 12 MESES) | J35: On Line | N35: Activo | O35: PAGOS ON LINE / CLEZ PAY-89000.00 | P35: 45937.335 | Q35: 7777777 | R35: CLEZ | U35: Factura de Venta | W35: Facturado automaticamente por CLEZ PAY (Cron cobro suscripcion) Facturado automaticamente por CLEZ PAY (Cron cobro suscripcion) | X35: No | Y35: Si | Z35: Renovado | AA35: Enviada | AB35: No | AC35: =IFERROR(VLOOKUP(C35,MigradosEfectivamente!B:B,1,FALSE),"No encontrado") -> No encontrado
A36: FPP-26892 | B36: NIXON CASTELLANOS | C36: 1127337039 | D36: br la argentina | E36: 3042907313 | F36: nameltrltr@gmail.com | G36: 89 | H36: Piedecuesta | I36: PLAN DEBITO AUTOMÃ¡TICO POR 89.000 (PERMANENCIA 12 MESES) | J36: On Line | N36: Activo | O36: PAGOS ON LINE / CLEZ PAY-89000.00 | P36: 45937.334 | Q36: 7777777 | R36: CLEZ | U36: Factura de Venta | W36: Facturado automaticamente por CLEZ PAY (Cron cobro suscripcion) Facturado automaticamente por CLEZ PAY (Cron cobro suscripcion) | X36: No | Y36: Si | Z36: Renovado | AA36: Enviada | AB36: No | AC36: =IFERROR(VLOOKUP(C36,MigradosEfectivamente!B:B,1,FALSE),"No encontrado") -> 1127337039
A37: FPNS-30929 | B37: MAYRA ALEJANDRA PAEZ TRILLOS | C37: 1090452609 | D37: Cucuta | E37: 3156001478 - 3168376158 | F37: MAYRAPAEZ92@GMAIL.COM | G37: 349 | H37: Cucuta | I37: CLEZ 4 MESES DELUXE | J37: On Line | N37: Activo | O37: PAGOS ON LINE / CLEZ PAY-349000.00 | P37: 45937.198 | Q37: 7777777 | R37: CLEZ | U37: Factura de Venta | W37: Facturado automaticamente por CLEZ PAY Facturado automaticamente por CLEZ PAY | X37: No | Y37: Si | Z37: Recuperado | AA37: Enviada | AB37: No | AC37: =IFERROR(VLOOKUP(C37,MigradosEfectivamente!B:B,1,FALSE),"No encontrado") -> No encontrado
A38: FP-34282 | B38: JHON EDINSON SIERRA CORREDOR | C38: 1092334876 | D38: bucaramanga | E38: 3123682469 | F38: jerjhon55@gmail.com | G38: 89 | H38: Provenza | I38: PLAN DEBITO AUTOMÃ¡TICO POR 99.000 (PERMANENCIA 12 MESES) | J38: On Line | N38: Activo | O38: PAGOS ON LINE / CLEZ PAY-89000.00 | P38: 45936.879 | Q38: 7777777 | R38: CLEZ | U38: Factura de Venta | W38: Facturado automaticamente por CLEZ PAY (Cron cobro suscripcion) Facturado automaticamente por CLEZ PAY (Cron cobro suscripcion) | X38: No | Y38: No | Z38: Renovado | AA38: Enviada | AB38: No | AC38: =IFERROR(VLOOKUP(C38,MigradosEfectivamente!B:B,1,FALSE),"No encontrado") -> No encontrado
A39: PR-1703 | B39: LEIDIS TRINIDAD BAQUERO DEL TORO | C39: 1193598878 | D39: Prado | E39: 3117999832 | F39: leidisbaquero33@gmail.com | G39: 89 | H39: El Prado | I39: PLAN DEBITO AUTOMÃ¡TICO POR 89.000 (PERMANENCIA 12 MESES) | J39: On Line | N39: Activo | O39: PAGOS ON LINE / CLEZ PAY-89000.00 | P39: 45936.875 | Q39: 7777777 | R39: CLEZ | U39: Factura de Venta | W39: Facturado automaticamente por CLEZ PAY (Cron cobro suscripcion) Facturado automaticamente por CLEZ PAY (Cron cobro suscripcion) | X39: No | Y39: Si | Z39: Renovado | AA39: Enviada | AB39: No | AC39: =IFERROR(VLOOKUP(C39,MigradosEfectivamente!B:B,1,FALSE),"No encontrado") -> No encontrado
A40: CB-8959 | B40: MARIA FERNANDA MOYA JIMENEZ | C40: 1098745697 | D40: BUCARAMANGA | E40: 3172917358 | F40: Mfmoya893@gmail.com | G40: 89 | H40: Cabecera | I40: PLAN DEBITO AUTOMÃ¡TICO POR 89.000 (PERMANENCIA 12 MESES) | J40: On Line | N40: Activo | O40: PAGOS ON LINE / CLEZ PAY-89000.00 | P40: 45936.875 | Q40: 7777777 | R40: CLEZ | U40: Factura de Venta | W40: Facturado automaticamente por CLEZ PAY (Cron cobro suscripcion) Facturado automaticamente por CLEZ PAY (Cron cobro suscripcion) | X40: No | Y40: Si | Z40: Renovado | AA40: No enviada | AB40: No | AC40: =IFERROR(VLOOKUP(C40,MigradosEfectivamente!B:B,1,FALSE),"No encontrado") -> No encontrado
A41: FPF-33441 | B41: ZULY CAROLINA SOCHA CABALLERO | C41: 1095925056 | D41: SAN FRANCISCO | E41: 3006413270 | F41: zulycarolina1@hotmail.com | G41: 591 | H41: Canaveral | I41: 13 MESES PREMIUM FP | J41: On Line | N41: Activo | O41: TARJETA CRÃ©DITO-591000.00 | P41: 45936.858 | Q41: 1232392469 | R41: MARIA VALENTINA RIVAS MORENO | T41: GREG JOSE JESUS ALVAREZ SUAREZ | U41: Factura de Venta | W41: R03243 R03243 | X41: Si | Y41: Si | Z41: Renovado | AA41: Enviada | AB41: No | AC41: =IFERROR(VLOOKUP(C41,MigradosEfectivamente!B:B,1,FALSE),"No encontrado") -> No encontrado
A42: FC-65827 | B42: YONATAN ARLEY CASTRO JURADO | C42: 1095580786 | D42: real de minas | E42: 3017811318 | F42: faico21937@gmail.com | G42: 99 | H42: Ciudadela | I42: PLAN DEBITO AUTOMÃ¡TICO POR 99.000 (PERMANENCIA 12 MESES) | J42: On Line | N42: Activo | O42: PAGOS ON LINE / CLEZ PAY-99000.00 | P42: 45936.336 | Q42: 7777777 | R42: CLEZ | U42: Factura de Venta | W42: Facturado automaticamente por CLEZ PAY (Cron cobro suscripcion) Facturado automaticamente por CLEZ PAY (Cron cobro suscripcion) | X42: No | Y42: Si | Z42: Renovado | AA42: Enviada | AB42: No | AC42: =IFERROR(VLOOKUP(C42,MigradosEfectivamente!B:B,1,FALSE),"No encontrado") -> No encontrado
A43: FPNS-30904 | B43: NORALBA NUÃ‘EZ ORDUZ | C43: 60263352 | D43: Parques residenciales b casa g7 | E43: 3202353678 | F43: yanamensajera@hotmail.com | G43: 89 | H43: Cucuta | I43: PLAN DEBITO AUTOMÃ¡TICO POR 89.000 (PERMANENCIA 12 MESES) | J43: On Line | N43: Activo | O43: PAGOS ON LINE / CLEZ PAY-89000.00 | P43: 45936.336 | Q43: 7777777 | R43: CLEZ | U43: Factura de Venta | W43: Facturado automaticamente por CLEZ PAY (Cron cobro suscripcion) Facturado automaticamente por CLEZ PAY (Cron cobro suscripcion) | X43: Si | Y43: Si | Z43: Renovado | AA43: Enviada | AB43: No | AC43: =IFERROR(VLOOKUP(C43,MigradosEfectivamente!B:B,1,FALSE),"No encontrado") -> No encontrado
A44: FPF-33423 | B44: JHON CONTRERAS | C44: 1063562400 | D44: carrera 18 # 11 - 43 edificio Ã¡tiko 18 | E44: 3152055741 | F44: theholyspiritandjohn@hotmail.com | G44: 99 | H44: Boulevard | I44: PLAN DEBITO AUTOMÃ¡TICO POR 99.000 (PERMANENCIA 12 MESES) | J44: On Line | N44: Activo | O44: PAGOS ON LINE / CLEZ PAY-99000.00 | P44: 45936.336 | Q44: 7777777 | R44: CLEZ | U44: Factura de Venta | W44: Facturado automaticamente por CLEZ PAY (Cron cobro suscripcion) Facturado automaticamente por CLEZ PAY (Cron cobro suscripcion) | X44: No | Y44: Si | Z44: Renovado | AA44: Enviada | AB44: No | AC44: =IFERROR(VLOOKUP(C44,MigradosEfectivamente!B:B,1,FALSE),"No encontrado") -> No encontrado
A45: FPF-33422 | B45: JHOAN STEBAN URUEÃ‘A GIRLADO | C45: 1000366072 | D45: Calle 19 #12-59 ciudad valencia | E45: 3118135811 | F45: jhoan.62.steban@gmail.com | G45: 89 | H45: Canaveral | I45: PLAN DEBITO AUTOMATICO LOS PRIMER 3 MESES $49.900 DESDE EL CUARTO MES 89.000 (PERMANENCIA 12 MESES) | J45: On Line | N45: Activo | O45: PAGOS ON LINE / CLEZ PAY-89000.00 | P45: 45936.334 | Q45: 7777777 | R45: CLEZ | U45: Factura de Venta | W45: Facturado automaticamente por CLEZ PAY (Cron cobro suscripcion) Facturado automaticamente por CLEZ PAY (Cron cobro suscripcion) | X45: Si | Y45: Si | Z45: Renovado | AA45: Enviada | AB45: No | AC45: =IFERROR(VLOOKUP(C45,MigradosEfectivamente!B:B,1,FALSE),"No encontrado") -> No encontrado
A46: CE-12369 | B46: PAULA VERA | C46: 1094245514 | D46: CEIBA II | E46: 3105552353 | F46: pendiente@gmail.com | G46: 89 | H46: Ceiba | I46: PLAN DEBITO AUTOMÃ¡TICO POR 89.000 (PERMANENCIA 12 MESES) | J46: On Line | N46: Activo | O46: PAGOS ON LINE / CLEZ PAY-89000.00 | P46: 45935.589 | Q46: 7777777 | R46: CLEZ | U46: Factura de Venta | W46: Facturado automaticamente por CLEZ PAY (Cron cobro suscripcion) Facturado automaticamente por CLEZ PAY (Cron cobro suscripcion) | X46: No | Y46: Si | Z46: Recuperado | AA46: No enviada | AB46: No | AC46: =IFERROR(VLOOKUP(C46,MigradosEfectivamente!B:B,1,FALSE),"No encontrado") -> No encontrado
A47: CE-12368 | B47: YURLEY KARIME CHONA CABALLERO | C47: 1090474602 | D47: BUCARAMANGA | E47: 3223284806 | F47: caballeroyurley26@gmail.com | G47: 99 | H47: Ceiba | I47: PLAN DEBITO AUTOMÃ¡TICO POR 99.000 (PERMANENCIA 12 MESES) | J47: On Line | N47: Activo | O47: PAGOS ON LINE / CLEZ PAY-99000.00 | P47: 45935.589 | Q47: 7777777 | R47: CLEZ | U47: Factura de Venta | W47: Facturado automaticamente por CLEZ PAY (Cron cobro suscripcion) Facturado automaticamente por CLEZ PAY (Cron cobro suscripcion) | X47: No | Y47: Si | Z47: Renovado | AA47: No enviada | AB47: No | AC47: =IFERROR(VLOOKUP(C47,MigradosEfectivamente!B:B,1,FALSE),"No encontrado") -> No encontrado
A48: FPF-33418 | B48: ROSA ESMERALDA ROJAS SERRANO | C48: 1005565212 | D48: BUCARAMANGA | E48: 573187360097 | F48: rojasserrano0528@gmail.com | G48: 89 | H48: Canaveral | I48: PLAN DEBITO AUTOMÃ¡TICO POR 89.000 (PERMANENCIA 12 MESES) | J48: On Line | N48: Activo | O48: PAGOS ON LINE / CLEZ PAY-89000.00 | P48: 45935.589 | Q48: 7777777 | R48: CLEZ | U48: Factura de Venta | W48: Facturado automaticamente por CLEZ PAY (Cron cobro suscripcion) Facturado automaticamente por CLEZ PAY (Cron cobro suscripcion) | X48: No | Y48: Si | Z48: Renovado | AA48: No enviada | AB48: No | AC48: =IFERROR(VLOOKUP(C48,MigradosEfectivamente!B:B,1,FALSE),"No encontrado") -> No encontrado
A49: FC-65826 | B49: JUAN DIEGO HORMIGA DIAZ | C49: 1102716825 | D49: CLL 59 #07-51 PLAZA SAN MARCOS | E49: 3015155229 | F49: hormigadiazjuandiego@gmail.com | G49: 99 | H49: Ciudadela | I49: PLAN DEBITO AUTOMÃ¡TICO POR 99.000 (PERMANENCIA 12 MESES) | J49: On Line | N49: Activo | O49: PAGOS ON LINE / CLEZ PAY-99000.00 | P49: 45935.585 | Q49: 7777777 | R49: CLEZ | U49: Factura de Venta | W49: Facturado automaticamente por CLEZ PAY (Cron cobro suscripcion) Facturado automaticamente por CLEZ PAY (Cron cobro suscripcion) | X49: Si | Y49: Si | Z49: Renovado | AA49: No enviada | AB49: No | AC49: =IFERROR(VLOOKUP(C49,MigradosEfectivamente!B:B,1,FALSE),"No encontrado") -> No encontrado
A50: FPNS-30897 | B50: MARIA JIMENEZ | C50: 1093590391 | D50: Calle 1d #5b-62 Bosques de Santa Barbara, Prados del Este | E50: 3228583462 | F50: mafecita502@gmail.com | G50: 89 | H50: Cucuta | I50: PLAN DEBITO AUTOMATICO LOS PRIMER 3 MESES $49.900 DESDE EL CUARTO MES 89.000 (PERMANENCIA 12 MESES) | J50: On Line | N50: Activo | O50: PAGOS ON LINE / CLEZ PAY-89000.00 | P50: 45935.584 | Q50: 7777777 | R50: CLEZ | U50: Factura de Venta | W50: Facturado automaticamente por CLEZ PAY (Cron cobro suscripcion) Facturado automaticamente por CLEZ PAY (Cron cobro suscripcion) | X50: No | Y50: Si | Z50: Renovado | AA50: No enviada | AB50: No | AC50: =IFERROR(VLOOKUP(C50,MigradosEfectivamente!B:B,1,FALSE),"No encontrado") -> No encontrado
A51: PR-1698 | B51: YEISON JAVIER LEON PUERTO | C51: 1101210988 | D51: SAN FRANCISCO | E51: 3004801938 | F51: yeisonleonpuerto@gmail.com | G51: 89 | H51: El Prado | I51: PLAN DEBITO AUTOMÃ¡TICO POR 89.000 (PERMANENCIA 12 MESES) | J51: On Line | N51: Activo | O51: PAGOS ON LINE / CLEZ PAY-89000.00 | P51: 45935.34 | Q51: 7777777 | R51: CLEZ | U51: Factura de Venta | W51: Facturado automaticamente por CLEZ PAY (Cron cobro suscripcion) Facturado automaticamente por CLEZ PAY (Cron cobro suscripcion) | X51: No | Y51: Si | Z51: Nuevo | AA51: No enviada | AB51: No | AC51: =IFERROR(VLOOKUP(C51,MigradosEfectivamente!B:B,1,FALSE),"No encontrado") -> No encontrado
A52: CE-12364 | B52: CLAUDIA DEL SOCORRO BENCARDINO LUNA | C52: 60345235 | D52: BUCARAMANGA | E52: 3219593735 | F52: claudiabencardino1971@gmail.com | G52: 89 | H52: Ceiba | I52: PLAN DEBITO AUTOMÃ¡TICO POR 89.000 (PERMANENCIA 12 MESES) | J52: On Line | N52: Activo | O52: PAGOS ON LINE / CLEZ PAY-89000.00 | P52: 45935.339 | Q52: 7777777 | R52: CLEZ | U52: Factura de Venta | W52: Facturado automaticamente por CLEZ PAY (Cron cobro suscripcion) Facturado automaticamente por CLEZ PAY (Cron cobro suscripcion) | X52: No | Y52: Si | Z52: Nuevo | AA52: No enviada | AB52: No | AC52: =IFERROR(VLOOKUP(C52,MigradosEfectivamente!B:B,1,FALSE),"No encontrado") -> No encontrado
A53: PR-1691 | B53: DUMAR PUENTES SALCEDO | C53: 1007470497 | D53: calle 31 #33a-60 | E53: 315 8937311 | F53: dumarpuentes007@gmail.com | G53: 89 | H53: El Prado | I53: PLAN DEBITO AUTOMÃ¡TICO POR 89.000 (PERMANENCIA 12 MESES) | J53: On Line | N53: Activo | O53: PAGOS ON LINE / CLEZ PAY-89000.00 | P53: 45934.339 | Q53: 7777777 | R53: CLEZ | U53: Factura de Venta | W53: Facturado automaticamente por CLEZ PAY (Cron cobro suscripcion) Facturado automaticamente por CLEZ PAY (Cron cobro suscripcion) | X53: No | Y53: Si | Z53: Recuperado | AA53: No enviada | AB53: No | AC53: =IFERROR(VLOOKUP(C53,MigradosEfectivamente!B:B,1,FALSE),"No encontrado") -> No encontrado
A54: FPNS-30884 | B54: ALMA LIZBETH HERNANDEZ CRIADO | C54: 60364174 | D54: CALLE 10 BN EL BOSQUE | E54: 3012675504 | F54: magistrada1911@gmail.com | G54: 89 | H54: Cucuta | I54: PLAN DEBITO AUTOMÃ¡TICO POR 89.000 (PERMANENCIA 12 MESES) | J54: On Line | N54: Activo | O54: PAGOS ON LINE / CLEZ PAY-89000.00 | P54: 45934.339 | Q54: 7777777 | R54: CLEZ | U54: Factura de Venta | W54: Facturado automaticamente por CLEZ PAY (Cron cobro suscripcion) Facturado automaticamente por CLEZ PAY (Cron cobro suscripcion) | X54: Si | Y54: Si | Z54: Recuperado | AA54: Enviada | AB54: No | AC54: =IFERROR(VLOOKUP(C54,MigradosEfectivamente!B:B,1,FALSE),"No encontrado") -> No encontrado
A55: CB-8917 | B55: ELIANA JOSEFINA SANCHEZ CASTILLO | C55: 1277816 | D55: BUCARAMANGA | E55: 3015667516 | F55: sanchezeliana293@gmail.com | G55: 89 | H55: Cabecera | I55: PLAN DEBITO AUTOMÃ¡TICO POR 99.000 (PERMANENCIA 12 MESES) | J55: On Line | N55: Activo | O55: PAGOS ON LINE / CLEZ PAY-89000.00 | P55: 45934.334 | Q55: 7777777 | R55: CLEZ | U55: Factura de Venta | W55: Facturado automaticamente por CLEZ PAY (Cron cobro suscripcion) Facturado automaticamente por CLEZ PAY (Cron cobro suscripcion) | X55: No | Y55: Si | Z55: Renovado | AA55: No enviada | AB55: No | AC55: =IFERROR(VLOOKUP(C55,MigradosEfectivamente!B:B,1,FALSE),"No encontrado") -> No encontrado
A56: 23531 | B56: JUNIOR ALEXIS BERMUDEZ | C56: 1102388335 | D56: PIEDECUESTA | E56: 3135860662 | F56: PENDIENTE@GMAIL.COM | G56: 99 | H56: DeLaCuesta | I56: PLAN DEBITO AUTOMÃ¡TICO POR 99.000 (PERMANENCIA 12 MESES) | J56: On Line | N56: Activo | O56: PAGOS ON LINE / CLEZ PAY-99000.00 | P56: 45934.334 | Q56: 7777777 | R56: CLEZ | U56: Factura de Venta | W56: Facturado automaticamente por CLEZ PAY (Cron cobro suscripcion) Facturado automaticamente por CLEZ PAY (Cron cobro suscripcion) | X56: Si | Y56: Si | Z56: Renovado | AA56: No enviada | AB56: No | AC56: =IFERROR(VLOOKUP(C56,MigradosEfectivamente!B:B,1,FALSE),"No encontrado") -> No encontrado
A57: FPF-33409 | B57: DAYRON JOSE QUINTERO CARVAJALINO | C57: 1004819048 | D57: cra 19 17 65 | E57: 3219684977 | F57: Dayron0951@gmail.com | G57: 89 | H57: Boulevard | I57: PLAN DEBITO AUTOMÃ¡TICO POR 89.000 (PERMANENCIA 12 MESES) | J57: On Line | N57: Activo | O57: PAGOS ON LINE / CLEZ PAY-89000.00 | P57: 45934.182 | Q57: 7777777 | R57: CLEZ | U57: Factura de Venta | W57: Facturado automaticamente por CLEZ PAY Facturado automaticamente por CLEZ PAY | X57: No | Y57: Si | Z57: Renovado | AA57: No enviada | AB57: No | AC57: =IFERROR(VLOOKUP(C57,MigradosEfectivamente!B:B,1,FALSE),"No encontrado") -> No encontrado
A58: FPNS-30882 | B58: CRISTIAN ANDRES SUMALAVE BONILLA | C58: 1193477337 | D58: PRADOS DEL ESTE | E58: 3208101240 | F58: CRISSUMBON@GMAIL.COM | G58: 89 | H58: Cucuta | I58: PLAN DEBITO AUTOMÃ¡TICO POR 89.000 (PERMANENCIA 12 MESES) | J58: On Line | N58: Activo | O58: PAGOS ON LINE / CLEZ PAY-89000.00 | P58: 45933.879 | Q58: 7777777 | R58: CLEZ | U58: Factura de Venta | W58: Facturado automaticamente por CLEZ PAY (Cron cobro suscripcion) Facturado automaticamente por CLEZ PAY (Cron cobro suscripcion) | X58: No | Y58: Si | Z58: Renovado | AA58: Enviada | AB58: No | AC58: =IFERROR(VLOOKUP(C58,MigradosEfectivamente!B:B,1,FALSE),"No encontrado") -> No encontrado
A59: FP-34262 | B59: ANGIE TATIANA MENDOZA CHAPARRO | C59: 1098768349 | D59: SAN FRANCISCO | E59: 322 7950622 | F59: angiemendoza270495@gmail.com | G59: 89 | H59: Provenza | I59: PLAN DEBITO AUTOMÃ¡TICO POR 89.000 (PERMANENCIA 12 MESES) | J59: On Line | N59: Activo | O59: PAGOS ON LINE / CLEZ PAY-89000.00 | P59: 45933.879 | Q59: 7777777 | R59: CLEZ | U59: Factura de Venta | W59: Facturado automaticamente por CLEZ PAY (Cron cobro suscripcion) Facturado automaticamente por CLEZ PAY (Cron cobro suscripcion) | X59: No | Y59: Si | Z59: Renovado | AA59: Enviada | AB59: No | AC59: =IFERROR(VLOOKUP(C59,MigradosEfectivamente!B:B,1,FALSE),"No encontrado") -> No encontrado
A60: FP-34255 | B60: JOSE ANGEL SABINO GARCIA | C60: 1081909917 | D60: Calle 113a 18 18 | E60: 3024874820 | F60: Josesabino0250@gmail.com | G60: 89 | H60: Provenza | I60: PLAN DEBITO AUTOMÃ¡TICO POR 99.000 (PERMANENCIA 12 MESES) | J60: On Line | N60: Activo | O60: PAGOS ON LINE / CLEZ PAY-89000.00 | P60: 45933.585 | Q60: 7777777 | R60: CLEZ | U60: Factura de Venta | W60: Facturado automaticamente por CLEZ PAY (Cron cobro suscripcion) Facturado automaticamente por CLEZ PAY (Cron cobro suscripcion) | X60: No | Y60: Si | Z60: Renovado | AA60: Enviada | AB60: No | AC60: =IFERROR(VLOOKUP(C60,MigradosEfectivamente!B:B,1,FALSE),"No encontrado") -> No encontrado
A61: CE-12345 | B61: BRAYAN ANDRES LOPEZ CONTRERAS | C61: 1090501397 | D61: CUCUTA | E61: 3168197952 | F61: brayan-andres97@hotmail.com | G61: 89 | H61: Ceiba | I61: PLAN DEBITO AUTOMÃ¡TICO POR 89.000 (PERMANENCIA 12 MESES) | J61: On Line | N61: Activo | O61: PAGOS ON LINE / CLEZ PAY-89000.00 | P61: 45933.34 | Q61: 7777777 | R61: CLEZ | U61: Factura de Venta | W61: Facturado automaticamente por CLEZ PAY (Cron cobro suscripcion) Facturado automaticamente por CLEZ PAY (Cron cobro suscripcion) | X61: Si | Y61: Si | Z61: Recuperado | AA61: Enviada | AB61: No | AC61: =IFERROR(VLOOKUP(C61,MigradosEfectivamente!B:B,1,FALSE),"No encontrado") -> No encontrado
A62: FPF-33396 | B62: ALISON YAMILETH NIÃ‘O MORA | C62: 1192923452 | D62: bucaramanga | E62: 3015991574 | F62: alimora1913@gmail.com | G62: 99 | H62: Boulevard | I62: PLAN DEBITO AUTOMÃ¡TICO POR 99.000 (PERMANENCIA 12 MESES) | J62: On Line | N62: Activo | O62: PAGOS ON LINE / CLEZ PAY-99000.00 | P62: 45933.34 | Q62: 7777777 | R62: CLEZ | U62: Factura de Venta | W62: Facturado automaticamente por CLEZ PAY (Cron cobro suscripcion) Facturado automaticamente por CLEZ PAY (Cron cobro suscripcion) | X62: Si | Y62: Si | Z62: Renovado | AA62: Enviada | AB62: No | AC62: =IFERROR(VLOOKUP(C62,MigradosEfectivamente!B:B,1,FALSE),"No encontrado") -> No encontrado
A63: FP-34251 | B63: JONATHAN JESSE CARVAJAL PALACIO | C63: 1098690840 | D63: CRA 13 # 103B -52 SANTAMARIA | E63: 3116518236 | F63: TOTANATOT@GMAIL.COM | G63: 89 | H63: Provenza | I63: PLAN DEBITO AUTOMÃ¡TICO POR 89.000 (PERMANENCIA 12 MESES) | J63: On Line | N63: Activo | O63: PAGOS ON LINE / CLEZ PAY-89000.00 | P63: 45933.34 | Q63: 7777777 | R63: CLEZ | U63: Factura de Venta | W63: Facturado automaticamente por CLEZ PAY (Cron cobro suscripcion) Facturado automaticamente por CLEZ PAY (Cron cobro suscripcion) | X63: Si | Y63: Si | Z63: Recuperado | AA63: Enviada | AB63: No | AC63: =IFERROR(VLOOKUP(C63,MigradosEfectivamente!B:B,1,FALSE),"No encontrado") -> No encontrado
A64: FPP-26873 | B64: YEISON DAVID CELIS CONDE | C64: 1193137458 | D64: AlcÃ³n de granada | E64: 312 5081790 | F64: jeisonceliscls@gmail.com | G64: 89 | H64: Piedecuesta | I64: PLAN DEBITO AUTOMÃ¡TICO POR 89.000 (PERMANENCIA 12 MESES) | J64: On Line | N64: Activo | O64: PAGOS ON LINE / CLEZ PAY-89000.00 | P64: 45933.339 | Q64: 7777777 | R64: CLEZ | U64: Factura de Venta | W64: Facturado automaticamente por CLEZ PAY (Cron cobro suscripcion) Facturado automaticamente por CLEZ PAY (Cron cobro suscripcion) | X64: Si | Y64: Si | Z64: Renovado | AA64: Enviada | AB64: No | AC64: =IFERROR(VLOOKUP(C64,MigradosEfectivamente!B:B,1,FALSE),"No encontrado") -> No encontrado
A65: FPNS-30870 | B65: CESAR VALERO | C65: 1090477739 | D65: Cll0an2e36 Quinta Bosh | E65: 3165350882 | F65: cavp211205@gmail.com | G65: 89 | H65: Cucuta | I65: PLAN DEBITO AUTOMÃ¡TICO POR 89.000 (PERMANENCIA 12 MESES) | J65: On Line | N65: Activo | O65: PAGOS ON LINE / CLEZ PAY-89000.00 | P65: 45933.338 | Q65: 7777777 | R65: CLEZ | U65: Factura de Venta | W65: Facturado automaticamente por CLEZ PAY (Cron cobro suscripcion) Facturado automaticamente por CLEZ PAY (Cron cobro suscripcion) | X65: No | Y65: Si | Z65: Renovado | AA65: Enviada | AB65: No | AC65: =IFERROR(VLOOKUP(C65,MigradosEfectivamente!B:B,1,FALSE),"No encontrado") -> No encontrado
A66: CE-12344 | B66: JERONIMO MEJIA | C66: 1054876715 | D66: CUCUTA | E66: 3225205446 | F66: JEROURBAN19@GMAIL.COM | G66: 99 | H66: Ceiba | I66: PLAN DEBITO AUTOMÃ¡TICO POR 99.000 (PERMANENCIA 12 MESES) | J66: On Line | N66: Activo | O66: PAGOS ON LINE / CLEZ PAY-99000.00 | P66: 45933.338 | Q66: 7777777 | R66: CLEZ | U66: Factura de Venta | W66: Facturado automaticamente por CLEZ PAY (Cron cobro suscripcion) Facturado automaticamente por CLEZ PAY (Cron cobro suscripcion) | X66: No | Y66: Si | Z66: Renovado | AA66: Enviada | AB66: No | AC66: =IFERROR(VLOOKUP(C66,MigradosEfectivamente!B:B,1,FALSE),"No encontrado") -> No encontrado
A67: PR-1684 | B67: EDGAR ANAYA TAME | C67: 13874553 | D67: cra47b30-34 | E67: 3112608984 | F67: edgaranaya1281@gmail.com | G67: 89 | H67: El Prado | I67: PLAN DEBITO AUTOMÃ¡TICO POR 89.000 (PERMANENCIA 12 MESES) | J67: On Line | N67: Activo | O67: PAGOS ON LINE / CLEZ PAY-89000.00 | P67: 45933.336 | Q67: 7777777 | R67: CLEZ | U67: Factura de Venta | W67: Facturado automaticamente por CLEZ PAY (Cron cobro suscripcion) Facturado automaticamente por CLEZ PAY (Cron cobro suscripcion) | X67: Si | Y67: Si | Z67: Renovado | AA67: Enviada | AB67: No | AC67: =IFERROR(VLOOKUP(C67,MigradosEfectivamente!B:B,1,FALSE),"No encontrado") -> No encontrado
A68: CE-12343 | B68: INGRID FABIOLA ALDANA OCHOA | C68: 60335443 | D68: Calle 6N 1AE35, Edificio Torre Club | E68: 3155838829 | F68: ifao2023@gmail.com | G68: 89 | H68: Ceiba | I68: PLAN DEBITO AUTOMÃ¡TICO POR 89.000 (PERMANENCIA 12 MESES) | J68: On Line | N68: Activo | O68: PAGOS ON LINE / CLEZ PAY-89000.00 | P68: 45933.336 | Q68: 7777777 | R68: CLEZ | U68: Factura de Venta | W68: Facturado automaticamente por CLEZ PAY (Cron cobro suscripcion) Facturado automaticamente por CLEZ PAY (Cron cobro suscripcion) | X68: No | Y68: Si | Z68: Renovado | AA68: Enviada | AB68: No | AC68: =IFERROR(VLOOKUP(C68,MigradosEfectivamente!B:B,1,FALSE),"No encontrado") -> No encontrado
A69: FP-34249 | B69: MAURICIO ZULUAGA | C69: 1096224121 | D69: Calle 61 15-13 edificio puerta mayor | E69: 3229707391 | F69: cartagenabga@gmail.com | G69: 89 | H69: Provenza | I69: PLAN DEBITO AUTOMÃ¡TICO POR 89.000 (PERMANENCIA 12 MESES) | J69: On Line | N69: Activo | O69: PAGOS ON LINE / CLEZ PAY-89000.00 | P69: 45933.335 | Q69: 7777777 | R69: CLEZ | U69: Factura de Venta | W69: Facturado automaticamente por CLEZ PAY (Cron cobro suscripcion) Facturado automaticamente por CLEZ PAY (Cron cobro suscripcion) | X69: No | Y69: Si | Z69: Renovado | AA69: Enviada | AB69: No | AC69: =IFERROR(VLOOKUP(C69,MigradosEfectivamente!B:B,1,FALSE),"No encontrado") -> No encontrado
A70: FPNS-30869 | B70: LEIDY JHURIANNY PARADA VELANDIA | C70: 1090466959 | D70: cucuta | E70: 3107738491 | F70: leidyparada21@gmail.com | G70: 89 | H70: Cucuta | I70: PLAN DEBITO AUTOMÃ¡TICO POR 89.000 (PERMANENCIA 12 MESES) | J70: On Line | N70: Activo | O70: PAGOS ON LINE / CLEZ PAY-89000.00 | P70: 45933.334 | Q70: 7777777 | R70: CLEZ | U70: Factura de Venta | W70: Facturado automaticamente por CLEZ PAY (Cron cobro suscripcion) Facturado automaticamente por CLEZ PAY (Cron cobro suscripcion) | X70: Si | Y70: Si | Z70: Renovado | AA70: Enviada | AB70: No | AC70: =IFERROR(VLOOKUP(C70,MigradosEfectivamente!B:B,1,FALSE),"No encontrado") -> No encontrado
A71: 23518 | B71: NATALIA VERGEL | C71: 1102378360 | D71: Cra 0cw 5n40 | E71: 3187821228 | F71: nvergel20@gmail.com | G71: 89 | H71: DeLaCuesta | I71: PLAN DEBITO AUTOMÃ¡TICO POR 89.000 (PERMANENCIA 12 MESES) | J71: On Line | N71: Activo | O71: PAGOS ON LINE / CLEZ PAY-89000.00 | P71: 45932.877 | Q71: 7777777 | R71: CLEZ | U71: Factura de Venta | W71: Facturado automaticamente por CLEZ PAY (Cron cobro suscripcion) Facturado automaticamente por CLEZ PAY (Cron cobro suscripcion) | X71: No | Y71: Si | Z71: Renovado | AA71: No enviada | AB71: No | AC71: =IFERROR(VLOOKUP(C71,MigradosEfectivamente!B:B,1,FALSE),"No encontrado") -> No encontrado
A72: FP-34247 | B72: ZHARICK HERRERA | C72: 1098618779 | D72: bella vista | E72: 3143085892 | F72: herrerazharick841@gmail.com | G72: 89 | H72: Provenza | I72: PLAN DEBITO AUTOMÃ¡TICO POR 89.000 (PERMANENCIA 12 MESES) | J72: On Line | N72: Activo | O72: PAGOS ON LINE / CLEZ PAY-89000.00 | P72: 45932.877 | Q72: 7777777 | R72: CLEZ | U72: Factura de Venta | W72: Facturado automaticamente por CLEZ PAY (Cron cobro suscripcion) Facturado automaticamente por CLEZ PAY (Cron cobro suscripcion) | X72: No | Y72: Si | Z72: Nuevo | AA72: No enviada | AB72: No | AC72: =IFERROR(VLOOKUP(C72,MigradosEfectivamente!B:B,1,FALSE),"No encontrado") -> No encontrado
A73: FPNS-30859 | B73: LORENT TATIANA QUINTERO PUERTO | C73: 1090524521 | D73: Dg 25 # 25-100 anillo vial occidental. Parques de bolivar 3. Torre 10-303 | E73: 3173506176 | F73: Loreley060715@gmail.com | G73: 89 | H73: Cucuta | I73: PLAN DEBITO AUTOMÃ¡TICO POR 89.000 (PERMANENCIA 12 MESES) | J73: On Line | N73: Activo | O73: PAGOS ON LINE / CLEZ PAY-89000.00 | P73: 45932.719 | Q73: 7777777 | R73: CLEZ | U73: Factura de Venta | W73: Facturado automaticamente por CLEZ PAY Facturado automaticamente por CLEZ PAY | X73: No | Y73: No | Z73: Nuevo | AA73: Enviada | AB73: No | AC73: =IFERROR(VLOOKUP(C73,MigradosEfectivamente!B:B,1,FALSE),"No encontrado") -> No encontrado
A74: FC-65802 | B74: ANA SOFIA AVELLANEDA ASPRILLA | C74: 1093592131 | D74: cll real #6-41 portal de san sebastian | E74: 3182760786 | F74: sofiaavellaneda2005@gmail.com | G74: 99 | H74: Ciudadela | I74: PLAN DEBITO AUTOMÃ¡TICO POR 99.000 (PERMANENCIA 12 MESES) | J74: On Line | N74: Activo | O74: PAGOS ON LINE / CLEZ PAY-99000.00 | P74: 45932.587 | Q74: 7777777 | R74: CLEZ | U74: Factura de Venta | W74: Facturado automaticamente por CLEZ PAY (Cron cobro suscripcion) Facturado automaticamente por CLEZ PAY (Cron cobro suscripcion) | X74: No | Y74: Si | Z74: Renovado | AA74: Enviada | AB74: No | AC74: =IFERROR(VLOOKUP(C74,MigradosEfectivamente!B:B,1,FALSE),"No encontrado") -> No encontrado
A75: 23517 | B75: JULIÃN ALEJANDRO ALMEIDA MORALES | C75: 1000505174 | D75: Calle 8n 4-150 | E75: 3016648508 | F75: alejandroalmeida9@gmail.com | G75: 99 | H75: DeLaCuesta | I75: PLAN DEBITO AUTOMÃ¡TICO POR 99.000 (PERMANENCIA 12 MESES) | J75: On Line | N75: Activo | O75: PAGOS ON LINE / CLEZ PAY-99000.00 | P75: 45932.584 | Q75: 7777777 | R75: CLEZ | U75: Factura de Venta | W75: Facturado automaticamente por CLEZ PAY (Cron cobro suscripcion) Facturado automaticamente por CLEZ PAY (Cron cobro suscripcion) | X75: No | Y75: Si | Z75: Renovado | AA75: No enviada | AB75: No | AC75: =IFERROR(VLOOKUP(C75,MigradosEfectivamente!B:B,1,FALSE),"No encontrado") -> No encontrado
A76: FC-65798 | B76: KAREN DAYANA SOTO VANEGAS | C76: 1116786909 | D76: Conjunto residencial samanes 6 | E76: 3204236265 | F76: karendsoto01@gmail.com | G76: 89 | H76: Ciudadela | I76: PLAN DEBITO AUTOMÃ¡TICO POR 89.000 (PERMANENCIA 12 MESES) | J76: On Line | N76: Activo | O76: PAGOS ON LINE / CLEZ PAY-89000.00 | P76: 45932.339 | Q76: 7777777 | R76: CLEZ | U76: Factura de Venta | W76: Facturado automaticamente por CLEZ PAY (Cron cobro suscripcion) Facturado automaticamente por CLEZ PAY (Cron cobro suscripcion) | X76: No | Y76: Si | Z76: Nuevo | AA76: No enviada | AB76: No | AC76: =IFERROR(VLOOKUP(C76,MigradosEfectivamente!B:B,1,FALSE),"No encontrado") -> No encontrado
A77: PR-1677 | B77: GINNEY ANDREA ARCINIEGAS ALFONSO | C77: 1098680141 | D77: BUCARAMANGA | E77: 3106839247 | F77: yamasa101619@gmail.com | G77: 89 | H77: El Prado | I77: PLAN DEBITO AUTOMÃ¡TICO POR 89.000 (PERMANENCIA 12 MESES) | J77: On Line | N77: Activo | O77: PAGOS ON LINE / CLEZ PAY-89000.00 | P77: 45932.339 | Q77: 7777777 | R77: CLEZ | U77: Factura de Venta | W77: Facturado automaticamente por CLEZ PAY (Cron cobro suscripcion) Facturado automaticamente por CLEZ PAY (Cron cobro suscripcion) | X77: No | Y77: Si | Z77: Nuevo | AA77: No enviada | AB77: No | AC77: =IFERROR(VLOOKUP(C77,MigradosEfectivamente!B:B,1,FALSE),"No encontrado") -> No encontrado
A78: FPNS-30854 | B78: CESAR ROSALES | C78: 1193130276 | D78: conjunto bilbao 302 t4 | E78: 3144540876 | F78: teamrolvis10@gmail.com | G78: 89 | H78: Cucuta | I78: PLAN DEBITO AUTOMÃ¡TICO POR 89.000 (PERMANENCIA 12 MESES) | J78: On Line | N78: Activo | O78: PAGOS ON LINE / CLEZ PAY-89000.00 | P78: 45932.338 | Q78: 7777777 | R78: CLEZ | U78: Factura de Venta | W78: Facturado automaticamente por CLEZ PAY (Cron cobro suscripcion) Facturado automaticamente por CLEZ PAY (Cron cobro suscripcion) | X78: No | Y78: Si | Z78: Nuevo | AA78: No enviada | AB78: No | AC78: =IFERROR(VLOOKUP(C78,MigradosEfectivamente!B:B,1,FALSE),"No encontrado") -> No encontrado
A79: FPNS-30853 | B79: LAURA ALVIS | C79: 1062957953 | D79: conjunto bilbao apto 302 t4 barrio la insula | E79: 3028452180 | F79: lauraalvis24@gmail.com | G79: 89 | H79: Cucuta | I79: PLAN DEBITO AUTOMÃ¡TICO POR 89.000 (PERMANENCIA 12 MESES) | J79: On Line | N79: Activo | O79: PAGOS ON LINE / CLEZ PAY-89000.00 | P79: 45932.338 | Q79: 7777777 | R79: CLEZ | U79: Factura de Venta | W79: Facturado automaticamente por CLEZ PAY (Cron cobro suscripcion) Facturado automaticamente por CLEZ PAY (Cron cobro suscripcion) | X79: No | Y79: Si | Z79: Nuevo | AA79: Enviada | AB79: No | AC79: =IFERROR(VLOOKUP(C79,MigradosEfectivamente!B:B,1,FALSE),"No encontrado") -> No encontrado
A80: PR-1676 | B80: LIZETH DELGADO | C80: 1007900671 | D80: Cll34#40-47 | E80: 3027393055 | F80: lizdanidelcon2430@gmail.com | G80: 89 | H80: El Prado | I80: PLAN DEBITO AUTOMÃ¡TICO POR 89.000 (PERMANENCIA 12 MESES) | J80: On Line | N80: Activo | O80: PAGOS ON LINE / CLEZ PAY-89000.00 | P80: 45932.338 | Q80: 7777777 | R80: CLEZ | U80: Factura de Venta | W80: Facturado automaticamente por CLEZ PAY (Cron cobro suscripcion) Facturado automaticamente por CLEZ PAY (Cron cobro suscripcion) | X80: No | Y80: Si | Z80: Nuevo | AA80: No enviada | AB80: No | AC80: =IFERROR(VLOOKUP(C80,MigradosEfectivamente!B:B,1,FALSE),"No encontrado") -> No encontrado
A81: PR-1675 | B81: DIANA LÃ“PEZ | C81: 1022342783 | D81: CALLE 17 # 51 C 50 MIRAFLORES | E81: 3023919516 | F81: gogotatan@hotmail.com | G81: 89 | H81: El Prado | I81: PLAN DEBITO AUTOMÃ¡TICO POR 89.000 (PERMANENCIA 12 MESES) | J81: On Line | N81: Activo | O81: PAGOS ON LINE / CLEZ PAY-89000.00 | P81: 45932.338 | Q81: 7777777 | R81: CLEZ | U81: Factura de Venta | W81: Facturado automaticamente por CLEZ PAY (Cron cobro suscripcion) Facturado automaticamente por CLEZ PAY (Cron cobro suscripcion) | X81: No | Y81: Si | Z81: Nuevo | AA81: No enviada | AB81: No | AC81: =IFERROR(VLOOKUP(C81,MigradosEfectivamente!B:B,1,FALSE),"No encontrado") -> No encontrado
A82: FPF-33392 | B82: CARLOS VILLARREAL | C82: 1216966032 | D82: Carrera 21 # 51 - 90 | E82: 3184363110 | F82: cavillarreal@unicesar.edu.co | G82: 99 | H82: Canaveral | I82: PLAN DEBITO AUTOMÃ¡TICO POR 99.000 (PERMANENCIA 12 MESES) | J82: On Line | N82: Activo | O82: PAGOS ON LINE / CLEZ PAY-99000.00 | P82: 45932.336 | Q82: 7777777 | R82: CLEZ | U82: Factura de Venta | W82: Facturado automaticamente por CLEZ PAY (Cron cobro suscripcion) Facturado automaticamente por CLEZ PAY (Cron cobro suscripcion) | X82: No | Y82: Si | Z82: Renovado | AA82: No enviada | AB82: No | AC82: =IFERROR(VLOOKUP(C82,MigradosEfectivamente!B:B,1,FALSE),"No encontrado") -> No encontrado
A83: FPNS-30852 | B83: SERGIO LAMUS | C83: 1093745009 | D83: Cll 8 Norte # 9E-11 | E83: 3107559097 | F83: lamussergio@gmail.com | G83: 89 | H83: Cucuta | I83: PLAN DEBITO AUTOMÃ¡TICO POR 99.000 (PERMANENCIA 12 MESES) | J83: On Line | N83: Activo | O83: PAGOS ON LINE / CLEZ PAY-89000.00 | P83: 45932.335 | Q83: 7777777 | R83: CLEZ | U83: Factura de Venta | W83: Facturado automaticamente por CLEZ PAY (Cron cobro suscripcion) Facturado automaticamente por CLEZ PAY (Cron cobro suscripcion) | X83: No | Y83: Si | Z83: Renovado | AA83: No enviada | AB83: No | AC83: =IFERROR(VLOOKUP(C83,MigradosEfectivamente!B:B,1,FALSE),"No encontrado") -> No encontrado
A84: CE-12331 | B84: DIANA MARIA VELANDIA HERNANDEZ | C84: 1098634365 | D84: puertachuelo | E84: 3144391712 | F84: Dianavelandiahernandez@gmail.com | G84: 89 | H84: Ceiba | I84: PLAN DEBITO AUTOMÃ¡TICO POR 99.000 (PERMANENCIA 12 MESES) | J84: On Line | N84: Activo | O84: PAGOS ON LINE / CLEZ PAY-89000.00 | P84: 45932.334 | Q84: 7777777 | R84: CLEZ | U84: Factura de Venta | W84: Facturado automaticamente por CLEZ PAY (Cron cobro suscripcion) Facturado automaticamente por CLEZ PAY (Cron cobro suscripcion) | X84: Si | Y84: Si | Z84: Renovado | AA84: No enviada | AB84: No | AC84: =IFERROR(VLOOKUP(C84,MigradosEfectivamente!B:B,1,FALSE),"No encontrado") -> No encontrado
A85: CB-8896 | B85: GABRIELA ALVAREZ FUENTES | C85: 1098825032 | D85: Calle 14#32a-24 | E85: 3102189351 | F85: gabyalfu99@gmail.com | G85: 89 | H85: Cabecera | I85: PLAN DEBITO AUTOMÃ¡TICO POR 99.000 (PERMANENCIA 12 MESES) | J85: On Line | N85: Activo | O85: PAGOS ON LINE / CLEZ PAY-89000.00 | P85: 45932.334 | Q85: 7777777 | R85: CLEZ | U85: Factura de Venta | W85: Facturado automaticamente por CLEZ PAY (Cron cobro suscripcion) Facturado automaticamente por CLEZ PAY (Cron cobro suscripcion) | X85: Si | Y85: Si | Z85: Renovado | AA85: Enviada | AB85: No | AC85: =IFERROR(VLOOKUP(C85,MigradosEfectivamente!B:B,1,FALSE),"No encontrado") -> No encontrado
A86: CE-12330 | B86: LUIS EDUARDO GUALDRON CRUZ | C86: 1090437770 | D86: CUCUTA | E86: 313 3345059 | F86: pendiente@gmail.com | G86: 349 | H86: Ceiba | I86: CLEZ 4 MESES DELUXE | J86: On Line | N86: Activo | O86: PAGOS ON LINE / CLEZ PAY-349000.00 | P86: 45932.027 | Q86: 7777777 | R86: CLEZ | U86: Factura de Venta | W86: Facturado automaticamente por CLEZ PAY Facturado automaticamente por CLEZ PAY | X86: Si | Y86: Si | Z86: Nuevo | AA86: No enviada | AB86: Si | AC86: =IFERROR(VLOOKUP(C86,MigradosEfectivamente!B:B,1,FALSE),"No encontrado") -> No encontrado
A87: CE-12329 | B87: JUAN DIEGO CASTILLA YAÃ‘EZ | C87: 1093795269 | D87: CALLE 3 N 0AE-12 LA CASTELLANA | E87: 3225130073 | F87: juandi1036@gmail.com | G87: 89 | H87: Ceiba | I87: PLAN DEBITO AUTOMÃ¡TICO POR 89.000 (PERMANENCIA 12 MESES) | J87: On Line | N87: Activo | O87: PAGOS ON LINE / CLEZ PAY-89000.00 | P87: 45931.876 | Q87: 7777777 | R87: CLEZ | U87: Factura de Venta | W87: Facturado automaticamente por CLEZ PAY (Cron cobro suscripcion) Facturado automaticamente por CLEZ PAY (Cron cobro suscripcion) | X87: Si | Y87: Si | Z87: Nuevo | AA87: Enviada | AB87: No | AC87: =IFERROR(VLOOKUP(C87,MigradosEfectivamente!B:B,1,FALSE),"No encontrado") -> No encontrado
A88: CE-12319 | B88: VALENTINA PRIETO PARRA | C88: 1117350603 | D88: tamarindo club | E88: 3113924522 | F88: valentinaprietoparra17@gmail.com | G88: 89 | H88: Ceiba | I88: PLAN DEBITO AUTOMÃ¡TICO POR 89.000 (PERMANENCIA 12 MESES) | J88: On Line | N88: Activo | O88: PAGOS ON LINE / CLEZ PAY-89000.00 | P88: 45931.584 | Q88: 7777777 | R88: CLEZ | U88: Factura de Venta | W88: Facturado automaticamente por CLEZ PAY (Cron cobro suscripcion) Facturado automaticamente por CLEZ PAY (Cron cobro suscripcion) | X88: Si | Y88: Si | Z88: Renovado | AA88: Enviada | AB88: No | AC88: =IFERROR(VLOOKUP(C88,MigradosEfectivamente!B:B,1,FALSE),"No encontrado") -> No encontrado
A89: FPF-33382 | B89: ANDRES FELIPE RODRIGUEZ GONZALEZ | C89: 1098752257 | D89: SAN FRANCISCO | E89: 3232068023 | F89: rodriguezgonandresfelipe36@gmail.com | G89: 89 | H89: Boulevard | I89: PLAN DEBITO AUTOMÃ¡TICO POR 89.000 (PERMANENCIA 12 MESES) | J89: On Line | N89: Activo | O89: PAGOS ON LINE / CLEZ PAY-89000.00 | P89: 45931.514 | Q89: 7777777 | R89: CLEZ | U89: Factura de Venta | W89: Facturado automaticamente por CLEZ PAY Facturado automaticamente por CLEZ PAY | X89: No | Y89: Si | Z89: Renovado | AA89: Enviada | AB89: No | AC89: =IFERROR(VLOOKUP(C89,MigradosEfectivamente!B:B,1,FALSE),"No encontrado") -> No encontrado
A90: FPP-26862 | B90: ANGIE ROBAYO JAIMES | C90: 1095838847 | D90: PIEDECUESTA | E90: 3143967220 | F90: angierobayo09@gmail.com | G90: 89 | H90: Piedecuesta | I90: PLAN DEBITO AUTOMÃ¡TICO POR 89.000 (PERMANENCIA 12 MESES) | J90: On Line | N90: Activo | O90: PAGOS ON LINE / CLEZ PAY-89000.00 | P90: 45931.508 | Q90: 7777777 | R90: CLEZ | U90: Factura de Venta | W90: Facturado automaticamente por CLEZ PAY Facturado automaticamente por CLEZ PAY | X90: Si | Y90: Si | Z90: Renovado | AA90: Enviada | AB90: No | AC90: =IFERROR(VLOOKUP(C90,MigradosEfectivamente!B:B,1,FALSE),"No encontrado") -> No encontrado
A91: FP-34232 | B91: NEYDER RICARDO ORTIZ PUERTA | C91: 1098821319 | D91: Provenza | E91: 3138053790 | F91: nrpuertaortiz28@gmail.com | G91: 89 | H91: Provenza | I91: PLAN DEBITO AUTOMÃ¡TICO POR 99.000 (PERMANENCIA 12 MESES) | J91: On Line | N91: Activo | O91: PAGOS ON LINE / CLEZ PAY-89000.00 | P91: 45931.34 | Q91: 7777777 | R91: CLEZ | U91: Factura de Venta | W91: Facturado automaticamente por CLEZ PAY (Cron cobro suscripcion) Facturado automaticamente por CLEZ PAY (Cron cobro suscripcion) | X91: Si | Y91: Si | Z91: Renovado | AA91: Enviada | AB91: No | AC91: =IFERROR(VLOOKUP(C91,MigradosEfectivamente!B:B,1,FALSE),"No encontrado") -> No encontrado
A92: CE-12304 | B92: PAULA VALENTINA LOSADA VILLANUEVA | C92: 1003965365 | D92: CALLE 6 N NUEMOR 12E 138 | E92: 3105323366 | F92: PAUVALENLANUTRI2003@GMAIL.COM | G92: 89 | H92: Ceiba | I92: PLAN DEBITO AUTOMÃ¡TICO POR 89.000 (PERMANENCIA 12 MESES) | J92: On Line | N92: Activo | O92: PAGOS ON LINE / CLEZ PAY-89000.00 | P92: 45931.337 | Q92: 7777777 | R92: CLEZ | U92: Factura de Venta | W92: Facturado automaticamente por CLEZ PAY (Cron cobro suscripcion) Facturado automaticamente por CLEZ PAY (Cron cobro suscripcion) | X92: Si | Y92: Si | Z92: Nuevo | AA92: Enviada | AB92: No | AC92: =IFERROR(VLOOKUP(C92,MigradosEfectivamente!B:B,1,FALSE),"No encontrado") -> No encontrado
A93: CB-8886 | B93: PEDRO ANDRES CARVAJAL CABALLERO | C93: 1098823605 | D93: bucaramanga | E93: NO QUIERE MAS INFORMACION | F93: notiene@gmail.com | G93: 89 | H93: Cabecera | I93: PLAN DEBITO AUTOMATICO LOS PRIMER 3 MESES $49.900 DESDE EL CUARTO MES 89.000 (PERMANENCIA 12 MESES) | J93: On Line | N93: Activo | O93: PAGOS ON LINE / CLEZ PAY-89000.00 | P93: 45931.336 | Q93: 7777777 | R93: CLEZ | U93: Factura de Venta | W93: Facturado automaticamente por CLEZ PAY (Cron cobro suscripcion) Facturado automaticamente por CLEZ PAY (Cron cobro suscripcion) | X93: No | Y93: Si | Z93: Renovado | AA93: Enviada | AB93: No | AC93: =IFERROR(VLOOKUP(C93,MigradosEfectivamente!B:B,1,FALSE),"No encontrado") -> No encontrado
A94: PR-1663 | B94: LEIDY TATIANA LOPEZ FLOREZ | C94: 1232888941 | D94: EL PRADO | E94: 315 2233135 | F94: Leidy_tatiana0710@hotmail.com | G94: 89 | H94: El Prado | I94: PLAN DEBITO AUTOMÃ¡TICO POR 89.000 (PERMANENCIA 12 MESES) | J94: On Line | N94: Activo | O94: PAGOS ON LINE / CLEZ PAY-89000.00 | P94: 45931.335 | Q94: 7777777 | R94: CLEZ | U94: Factura de Venta | W94: Facturado automaticamente por CLEZ PAY (Cron cobro suscripcion) Facturado automaticamente por CLEZ PAY (Cron cobro suscripcion) | X94: Si | Y94: Si | Z94: Nuevo | AA94: Enviada | AB94: No | AC94: =IFERROR(VLOOKUP(C94,MigradosEfectivamente!B:B,1,FALSE),"No encontrado") -> No encontrado
A95: FC-65779 | B95: YURLAINY HERNANDEZ | C95: 1002157468 | D95: calle 59 1w-36 MUTIS | E95: 3148374234 | F95: yurla2340@gmail.com | G95: 89 | H95: Ciudadela | I95: PLAN DEBITO AUTOMATICO LOS PRIMER 3 MESES $49.900 DESDE EL CUARTO MES 89.000 (PERMANENCIA 12 MESES) | J95: On Line | N95: Activo | O95: PAGOS ON LINE / CLEZ PAY-89000.00 | P95: 45931.334 | Q95: 7777777 | R95: CLEZ | U95: Factura de Venta | W95: Facturado automaticamente por CLEZ PAY (Cron cobro suscripcion) Facturado automaticamente por CLEZ PAY (Cron cobro suscripcion) | X95: No | Y95: Si | Z95: Renovado | AA95: Enviada | AB95: No | AC95: =IFERROR(VLOOKUP(C95,MigradosEfectivamente!B:B,1,FALSE),"No encontrado") -> No encontrado
A96: FPNS-30837 | B96: MARIA ANGELICA CASTRO SILVA | C96: 1004926021 | D96: Cucuta | E96: 3244181548 | F96: mariacastro192003@gmail.com | G96: 99 | H96: Cucuta | I96: PLAN DEBITO AUTOMÃ¡TICO POR 99.000 (PERMANENCIA 12 MESES) | J96: On Line | N96: Activo | O96: PAGOS ON LINE / CLEZ PAY-99000.00 | P96: 45931.334 | Q96: 7777777 | R96: CLEZ | U96: Factura de Venta | W96: Facturado automaticamente por CLEZ PAY (Cron cobro suscripcion) Facturado automaticamente por CLEZ PAY (Cron cobro suscripcion) | X96: No | Y96: Si | Z96: Renovado | AA96: Enviada | AB96: No | AC96: =IFERROR(VLOOKUP(C96,MigradosEfectivamente!B:B,1,FALSE),"No encontrado") -> No encontrado
A97: FV-16287 | B97: SARA SUAREZ AGUILAR | C97: 1104068868 | D97: Cabecera | E97: 316 4788609 | F97: Sarasuarez39@gmail.com | G97: 349 | H97: Online | I97: 4 MESES DELUXE | J97: On Line | N97: Activo | O97: PAGOS ON LINE / PAYU -349000.00 | P97: 45930.938 | Q97: 1097096498 | R97: JUAN DAVID RINCON GOMEZ | T97: GREG JOSE JESUS ALVAREZ SUAREZ | U97: Factura de Venta | X97: No | Y97: Si | Z97: Nuevo | AA97: Enviada | AB97: No | AC97: =IFERROR(VLOOKUP(C97,MigradosEfectivamente!B:B,1,FALSE),"No encontrado") -> No encontrado
A98: FV-16286 | B98: ROBERT DANILO DIAZ ARDILA | C98: 1005163557 | D98: cabecera | E98: 3155173057 | F98: pendiente@gmail.com | G98: 500 | H98: Online | I98: 8 MESES DELUXE | J98: On Line | N98: Activo | O98: TRANSFERENCIA BANCARIA-500000.00 | P98: 45930.876 | Q98: 1007382904 | R98: EDINSON HELI HERNANDEZ ACEVEDO | T98: GREG JOSE JESUS ALVAREZ SUAREZ | U98: Factura de Venta | X98: No | Y98: Si | Z98: Recuperado | AA98: Enviada | AB98: Si | AC98: =IFERROR(VLOOKUP(C98,MigradosEfectivamente!B:B,1,FALSE),"No encontrado") -> No encontrado
A99: CE-12291 | B99: INGRY KATERINE ROJAS RODRIGUEZ | C99: 1093908575 | D99: BUCARAMANGA | E99: 3143184325 | F99: Ingrykaterinerojas@gmail.com | G99: 500 | H99: Ceiba | I99: 8 MESES DELUXE | J99: On Line | N99: Activo | O99: TARJETA DÃ©BITO-500000.00 | P99: 45930.764 | Q99: 1232392469 | R99: MARIA VALENTINA RIVAS MORENO | U99: Factura de Venta | X99: No | Y99: Si | Z99: Nuevo | AA99: Enviada | AB99: Si | AC99: =IFERROR(VLOOKUP(C99,MigradosEfectivamente!B:B,1,FALSE),"No encontrado") -> No encontrado
A100: CE-12285 | B100: MIGUEL BERMUDEZ | C100: 1004808410 | D100: Av libertadores 10bn 76 edificio florimar | E100: 3224611612 | F100: Miguelbermudez664@gmail.com | G100: 99 | H100: Ceiba | I100: PLAN DEBITO AUTOMÃ¡TICO POR 99.000 (PERMANENCIA 12 MESES) | J100: On Line | N100: Activo | O100: PAGOS ON LINE / CLEZ PAY-99000.00 | P100: 45930.439 | Q100: 7777777 | R100: CLEZ | U100: Factura de Venta | W100: Facturado automaticamente por CLEZ PAY Facturado automaticamente por CLEZ PAY | X100: No | Y100: Si | Z100: Nuevo | AA100: Enviada | AB100: No | AC100: =IFERROR(VLOOKUP(C100,MigradosEfectivamente!B:B,1,FALSE),"No encontrado") -> No encontrado
...

Sheet MigradosEfectivamente
A1: IdAfiliado | B1: DocumentoAfiliado | C1: idTipoDocumento | D1: NombreAfiliado | E1: ApellidoAfiliado | F1: CelularAfiliado | G1: EmailAfiliado | H1: ClaveAfiliado | I1: DireccionAfiliado | J1: idCiudadAfiliado | K1: FechaNacAfiliado | L1: FotoAfiliado | M1: idGenero | N1: idSede | O1: idEstadoCivilAfiliado | P1: idEmpresaAfil | Q1: idProfesion | R1: idEPS | S1: ResponsableAfiliado | T1: Parentesco | U1: ContactoAfiliado | V1: idUsuario | W1: EstadoAfiliado | X1: FechaAfiliacion | Y1: ProcesoActFecNac | Z1: ObservacionesParQ | AA1: Columna1
A2: 2135 | B2: 1098682492 | C2: 3 | D2: Daniel Felipe | E2: Quijano Dominguez | F2: 3164353062 | G2: quijanodominguezdanielfelipe@gmail.com | H2: \N | I2: \N | J2: 1 | K2: 39483 | L2: \N | M2: 1 | N2: 10 | O2: \N | P2: \N | Q2: \N | R2: \N | S2: \N | T2: \N | U2: \N | V2: \N | W2: Pendiente | X2: 45916 | Y2: 0 | Z2: \N | AA2: =IFERROR(VLOOKUP(B2,BD_Clez_Premigracion!C:C,1,FALSE),"No encontrado") -> 1098682492
A3: 2136 | B3: 1030542921 | C3: 1 | D3: VALENTINA | E3: SAAVEDRA HOYOS | F3: 3196218540 | G3: valentinahoyos77@gmail.com | H3: \N | I3: \N | J3: 1 | K3: 38041 | L3: \N | M3: 2 | N3: 10 | O3: \N | P3: \N | Q3: \N | R3: \N | S3: \N | T3: \N | U3: \N | V3: \N | W3: Pendiente | X3: 45916 | Y3: 0 | Z3: \N | AA3: =IFERROR(VLOOKUP(B3,BD_Clez_Premigracion!C:C,1,FALSE),"No encontrado") -> 1030542921
A4: 2137 | B4: 1098649193 | C4: 1 | D4: ALEXANDRA | E4: GELVEZ ROJAS | F4: 3102944662 | G4: Alexandrag54@hotmail.com | H4: \N | I4: \N | J4: 1 | K4: 32180 | L4: \N | M4: 2 | N4: 8 | O4: \N | P4: \N | Q4: \N | R4: \N | S4: \N | T4: \N | U4: \N | V4: \N | W4: Pendiente | X4: 45916 | Y4: 0 | Z4: \N | AA4: =IFERROR(VLOOKUP(B4,BD_Clez_Premigracion!C:C,1,FALSE),"No encontrado") -> 1098649193
A5: 2138 | B5: 1098635512 | C5: 1 | D5: SANTIAGO SNEIDER | E5: VILLAMIZAR LOPEZ | F5: 3169075502 | G5: santiagovillamizar500@gmail.com | H5: \N | I5: \N | J5: 1 | K5: 38459 | L5: \N | M5: 1 | N5: 10 | O5: \N | P5: \N | Q5: \N | R5: \N | S5: \N | T5: \N | U5: \N | V5: \N | W5: Pendiente | X5: 45916 | Y5: 0 | Z5: \N | AA5: =IFERROR(VLOOKUP(B5,BD_Clez_Premigracion!C:C,1,FALSE),"No encontrado") -> No encontrado
A6: 2144 | B6: 1098800251 | C6: 1 | D6: ALEJANDRA | E6: PINILLA MELENDEZ | F6: 3178539153 | G6: alejandrapinilla_97@hotmail.com | H6: \N | I6: \N | J6: 1 | K6: 35684 | L6: \N | M6: 2 | N6: 8 | O6: \N | P6: \N | Q6: \N | R6: \N | S6: \N | T6: \N | U6: \N | V6: \N | W6: Pendiente | X6: 45917 | Y6: 0 | Z6: \N | AA6: =IFERROR(VLOOKUP(B6,BD_Clez_Premigracion!C:C,1,FALSE),"No encontrado") -> No encontrado
A7: 2148 | B7: 1140831066 | C7: 1 | D7: ERIC DANIEL | E7: RIVALDO CORONELL | F7: 3115430198 | G7: ericrivaldocoronell@gmail.com | H7: \N | I7: \N | J7: 1 | K7: 33045 | L7: \N | M7: 1 | N7: 8 | O7: \N | P7: \N | Q7: \N | R7: \N | S7: \N | T7: \N | U7: \N | V7: \N | W7: Pendiente | X7: 45917 | Y7: 0 | Z7: \N | AA7: =IFERROR(VLOOKUP(B7,BD_Clez_Premigracion!C:C,1,FALSE),"No encontrado") -> No encontrado
A8: 2152 | B8: 1097182426 | C8: 1 | D8: PAULA ANDREA | E8: AGUIRRE RINCON | F8: 3219316506 | G8: andreitaaguirre08@gmail.com | H8: \N | I8: \N | J8: 1 | K8: 38204 | L8: \N | M8: 2 | N8: 8 | O8: \N | P8: \N | Q8: \N | R8: \N | S8: \N | T8: \N | U8: \N | V8: \N | W8: Pendiente | X8: 45917 | Y8: 0 | Z8: \N | AA8: =IFERROR(VLOOKUP(B8,BD_Clez_Premigracion!C:C,1,FALSE),"No encontrado") -> No encontrado
A9: 2139 | B9: 5081664 | C9: 6 | D9: Yayre | E9: Quintero Sánchez | F9: 3505347893 | G9: yayrels@gmail.com | H9: \N | I9: \N | J9: 1 | K9: 35466 | L9: \N | M9: 2 | N9: 10 | O9: \N | P9: \N | Q9: \N | R9: \N | S9: \N | T9: \N | U9: \N | V9: \N | W9: Activo | X9: 45916 | Y9: 0 | Z9: \N | AA9: =IFERROR(VLOOKUP(B9,BD_Clez_Premigracion!C:C,1,FALSE),"No encontrado") -> No encontrado
A10: 2153 | B10: 1193374427 | C10: 1 | D10: LAURA CAMILA | E10: RANGEL CARDENAS | F10: 3197647367 | G10: laurangcard@hotmail.com | H10: \N | I10: \N | J10: 4 | K10: 36909 | L10: \N | M10: 2 | N10: 6 | O10: \N | P10: \N | Q10: \N | R10: \N | S10: \N | T10: \N | U10: \N | V10: \N | W10: Pendiente | X10: 45918 | Y10: 0 | Z10: \N | AA10: =IFERROR(VLOOKUP(B10,BD_Clez_Premigracion!C:C,1,FALSE),"No encontrado") -> 1193374427
A11: 2156 | B11: 1093777011 | C11: 1 | D11: CARLOS HUMBERTO | E11: FIGUEROA ANGARITA | F11: 3224020128 | G11: Carlosfangarita001@gmail.com | H11: \N | I11: \N | J11: 4 | K11: 34735 | L11: \N | M11: 1 | N11: 6 | O11: \N | P11: \N | Q11: \N | R11: \N | S11: \N | T11: \N | U11: \N | V11: \N | W11: Pendiente | X11: 45918 | Y11: 0 | Z11: \N | AA11: =IFERROR(VLOOKUP(B11,BD_Clez_Premigracion!C:C,1,FALSE),"No encontrado") -> No encontrado
A12: 2157 | B12: 1102714541 | C12: 1 | D12: JHOAN JOSE | E12: TOLEDO VERA | F12: 3153186367 | G12: Jjosetoledo1991@gmail.com | H12: \N | I12: \N | J12: 1 | K12: 33323 | L12: \N | M12: 1 | N12: 2 | O12: \N | P12: \N | Q12: \N | R12: \N | S12: \N | T12: \N | U12: \N | V12: \N | W12: Pendiente | X12: 45918 | Y12: 0 | Z12: \N | AA12: =IFERROR(VLOOKUP(B12,BD_Clez_Premigracion!C:C,1,FALSE),"No encontrado") -> 1102714541
A13: 2158 | B13: 1098822746 | C13: 1 | D13: SEBASTIAN | E13: LOPEZ RUEDA | F13: 3187252767 | G13: Sebaslopezru7@gmail.com | H13: \N | I13: \N | J13: 1 | K13: 36375 | L13: \N | M13: 1 | N13: 2 | O13: \N | P13: \N | Q13: \N | R13: \N | S13: \N | T13: \N | U13: \N | V13: \N | W13: Pendiente | X13: 45918 | Y13: 0 | Z13: \N | AA13: =IFERROR(VLOOKUP(B13,BD_Clez_Premigracion!C:C,1,FALSE),"No encontrado") -> No encontrado
... A23: 2145 | B23: 108797587 | C23: 4 | D23: José Andrés | E23: Vera peña | F23: 3204669676 | G23: Veraandresoficial@gmail.com | H23: \N | I23: \N | J23: 1 | K23: 35553 | L23: \N | M23: 1 | N23: 8 | O23: \N | P23: \N | Q23: \N | R23: \N | S23: \N | T23: \N | U23: \N | V23: \N | W23: Pendiente | X23: 45917 | Y23: 0 | Z23: \N | AA23: =IFERROR(VLOOKUP(B23,BD_Clez_Premigracion!C:C,1,FALSE),"No encontrado") -> No encontrado
A24: 2176 | B24: 1005372165 | C24: 1 | D24: ANA CAMILA | E24: CAAMAÑO DIAZ | F24: 3124778011 | G24: camilacd0926@gmail.com | H24: \N | I24: Calle 8 # 11-47 | J24: 2 | K24: 37020 | L24: \N | M24: 2 | N24: 3 | O24: \N | P24: \N | Q24: \N | R24: 4 | S24: Samuel Caamaño | T24: Hermano/a | U24: 3172798847 | V24: \N | W24: Activo | X24: 45921 | Y24: 0 | AA24: =IFERROR(VLOOKUP(B24,BD_Clez_Premigracion!C:C,1,FALSE),"No encontrado") -> No encontrado
A25: 2177 | B25: 1102376249 | C25: 1 | D25: Katherine | E25: Rodriguez santiago | F25: 3117076240 | G25: Kathesantiago29@gmail.com | H25: \N | I25: \N | J25: 3 | K25: 34728 | L25: \N | M25: 2 | N25: 5 | O25: \N | P25: \N | Q25: \N | R25: \N | S25: \N | T25: \N | U25: \N | V25: \N | W25: Pendiente | X25: 45921 | Y25: 0 | Z25: \N | AA25: =IFERROR(VLOOKUP(B25,BD_Clez_Premigracion!C:C,1,FALSE),"No encontrado") -> No encontrado
A26: 2141 | B26: 1095831653 | C26: 1 | D26: ANGIE STEFANIA | E26: QUIJANO PLATA | F26: 3144438697 | G26: tatisplata9@gmail.com | H26: \N | I26: \N | J26: 1 | K26: 35388 | L26: \N | M26: 2 | N26: 2 | O26: \N | P26: \N | Q26: \N | R26: \N | S26: \N | T26: \N | U26: \N | V26: \N | W26: Pendiente | X26: 45916 | Y26: 0 | Z26: \N | AA26: =IFERROR(VLOOKUP(B26,BD_Clez_Premigracion!C:C,1,FALSE),"No encontrado") -> 1095831653
A27: 2178 | B27: 1092386369 | C27: 1 | D27: EDUARDO ANDRES | E27: RAMIREZ CARDENAS | F27: 3142927674 | G27: Eduardoandres_1998@hotmail.com | H27: \N | I27: Villas de Montecarlo casa C10 | J27: \N | K27: 35985 | L27: \N | M27: 1 | N27: 4 | O27: \N | P27: \N | Q27: \N | R27: 1 | S27: Luz cardneas | T27: Padre/Madre | U27: 3124528163 | V27: \N | W27: Activo | X27: 45922 | Y27: 0 | AA27: =IFERROR(VLOOKUP(B27,BD_Clez_Premigracion!C:C,1,FALSE),"No encontrado") -> No encontrado
A28: 2179 | B28: 1148221342 | C28: 1 | D28: KEVIN EDUARDO | E28: ALVAREZ DIAZ | F28: 3028050235 | G28: kevtraderve@gmail.com | H28: \N | I28: \N | J28: \N | K28: 36577 | L28: \N | M28: 1 | N28: 6 | O28: \N | P28: \N | Q28: \N | R28: \N | S28: \N | T28: \N | U28: \N | V28: \N | W28: Pendiente | X28: 45922 | Y28: 0 | Z28: \N | AA28: =IFERROR(VLOOKUP(B28,BD_Clez_Premigracion!C:C,1,FALSE),"No encontrado") -> No encontrado
A29: 2180 | B29: 1005257154 | C29: 1 | D29: GABRIEL ALEJANDRO | E29: VELA MARTINEZ | F29: 3150675863 | G29: gabriel.alejandro125@gmail.com | H29: \N | I29: \N | J29: \N | K29: 37128 | L29: \N | M29: 1 | N29: 1 | O29: \N | P29: \N | Q29: \N | R29: \N | S29: \N | T29: \N | U29: \N | V29: \N | W29: Pendiente | X29: 45922 | Y29: 0 | Z29: \N | AA29: =IFERROR(VLOOKUP(B29,BD_Clez_Premigracion!C:C,1,FALSE),"No encontrado") -> 1005257154
A30: 2181 | B30: 1093854460 | C30: 1 | D30: ERIC SAMUEL | E30: SUAREZ NUÑEZ | F30: 3028502200 | G30: Yanamensajera@hotmail.com | H30: \N | I30: \N | J30: \N | K30: 38225 | L30: \N | M30: 1 | N30: 6 | O30: \N | P30: \N | Q30: \N | R30: \N | S30: \N | T30: \N | U30: \N | V30: \N | W30: Pendiente | X30: 45922 | Y30: 0 | Z30: \N | AA30: =IFERROR(VLOOKUP(B30,BD_Clez_Premigracion!C:C,1,FALSE),"No encontrado") -> No encontrado
A31: 2182 | B31: 1126424740 | C31: 1 | D31: PAULO CESAR | E31: RINCON NAVARRO | F31: 3228742598 | G31: paulorinconpr88@gmail.com | H31: \N | I31: \N | J31: \N | K31: 26839 | L31: \N | M31: 1 | N31: 4 | O31: \N | P31: \N | Q31: \N | R31: \N | S31: \N | T31: \N | U31: \N | V31: \N | W31: Pendiente | X31: 45922 | Y31: 0 | Z31: \N | AA31: =IFERROR(VLOOKUP(B31,BD_Clez_Premigracion!C:C,1,FALSE),"No encontrado") -> No encontrado
A32: 2188 | B32: 1095837324 | C32: 1 | D32: Jefferson Julian | E32: Gonzalez Bueno | F32: 3153795088 | G32: Julian1327gonzalez@gmail.com | H32: \N | I32: \N | J32: \N | K32: 35867 | L32: \N | M32: 1 | N32: 5 | O32: \N | P32: \N | Q32: \N | R32: \N | S32: \N | T32: \N | U32: \N | V32: \N | W32: Pendiente | X32: 45923 | Y32: 0 | Z32: \N | AA32: =IFERROR(VLOOKUP(B32,BD_Clez_Premigracion!C:C,1,FALSE),"No encontrado") -> No encontrado
A33: 2185 | B33: 1098766559 | C33: 1 | D33: KAREN ALICIA | E33: PABON RIATIGA | F33: 3212371879 | G33: aliciapabon1994@gmail.com | H33: \N | I33: \N | J33: \N | K33: 34669 | L33: \N | M33: 2 | N33: 8 | O33: \N | P33: \N | Q33: \N | R33: \N | S33: \N | T33: \N | U33: \N | V33: \N | W33: Pendiente | X33: 45922 | Y33: 0 | Z33: \N | AA33: =IFERROR(VLOOKUP(B33,BD_Clez_Premigracion!C:C,1,FALSE),"No encontrado") -> No encontrado
A34: 2184 | B34: 1005199841 | C34: 1 | D34: MICHELL KATHERINE | E34: SOLANO GELVEZ | F34: 3181652462 | G34: kgelvez2002@gmail.com | H34: \N | I34: \N | J34: \N | K34: 37447 | L34: \N | M34: 2 | N34: 1 | O34: \N | P34: \N | Q34: \N | R34: \N | S34: \N | T34: \N | U34: \N | V34: \N | W34: Pendiente | X34: 45922 | Y34: 0 | Z34: \N | AA34: =IFERROR(VLOOKUP(B34,BD_Clez_Premigracion!C:C,1,FALSE),"No encontrado") -> 1005199841
A35: 2189 | B35: 1098805509 | C35: 1 | D35: JUAN JOSE | E35: DUARTE RODRIGUEZ | F35: 3132298289 | G35: duarte9701@gmail.com | H35: \N | I35: \N | J35: \N | K35: 35704 | L35: \N | M35: 1 | N35: 6 | O35: \N | P35: \N | Q35: \N | R35: \N | S35: \N | T35: \N | U35: \N | V35: \N | W35: Pendiente | X35: 45923 | Y35: 0 | Z35: \N | AA35: =IFERROR(VLOOKUP(B35,BD_Clez_Premigracion!C:C,1,FALSE),"No encontrado") -> No encontrado
A36: 2191 | B36: 22798614 | C36: 1 | D36: HILDEGARDE LUCILA | E36: CORREAL RUEDA | F36: 3168950806 | G36: hildegarde1979@hotmail.com | H36: \N | I36: \N | J36: \N | K36: 28974 | L36: \N | M36: 2 | N36: 10 | O36: \N | P36: \N | Q36: \N | R36: \N | S36: \N | T36: \N | U36: \N | V36: \N | W36: Pendiente | X36: 45923 | Y36: 0 | Z36: \N | AA36: =IFERROR(VLOOKUP(B36,BD_Clez_Premigracion!C:C,1,FALSE),"No encontrado") -> No encontrado
A37: 2192 | B37: 1006372165 | C37: 1 | D37: Ana Camila | E37: Caamaño Diaz | F37: 3124778011 | G37: camilacd0926@gmail.com | H37: \N | I37: \N | J37: \N | K37: 37020 | L37: \N | M37: 2 | N37: 3 | O37: \N | P37: \N | Q37: \N | R37: \N | S37: \N | T37: \N | U37: \N | V37: \N | W37: Pendiente | X37: 45924 | Y37: 0 | Z37: \N | AA37: =IFERROR(VLOOKUP(B37,BD_Clez_Premigracion!C:C,1,FALSE),"No encontrado") -> No encontrado
A38: 2193 | B38: 1095949447 | C38: 1 | D38: EDER FABIAN | E38: NIETO LEON | F38: 3177227375 | G38: ederfabiannieto@gmail.com | H38: \N | I38: \N | J38: \N | K38: 35658 | L38: \N | M38: 1 | N38: 8 | O38: \N | P38: \N | Q38: \N | R38: \N | S38: \N | T38: \N | U38: \N | V38: \N | W38: Pendiente | X38: 45924 | Y38: 0 | Z38: \N | AA38: =IFERROR(VLOOKUP(B38,BD_Clez_Premigracion!C:C,1,FALSE),"No encontrado") -> 1095949447
A39: 2196 | B39: 1091354733 | C39: 1 | D39: MARIA FERNANDA | E39: ECHEVERRI JOYA | F39: 3188213670 | G39: mafe.ej1823@gmail.com | H39: \N | I39: \N | J39: \N | K39: 38429 | L39: \N | M39: 2 | N39: 6 | O39: \N | P39: \N | Q39: \N | R39: \N | S39: \N | T39: \N | U39: \N | V39: \N | W39: Pendiente | X39: 45924 | Y39: 0 | Z39: \N | AA39: =IFERROR(VLOOKUP(B39,BD_Clez_Premigracion!C:C,1,FALSE),"No encontrado") -> 1091354733
... A61: 2231 | B61: 1095300596 | C61: 1 | D61: Sirley | E61: Ardila | F61: 3185197630 | G61: ardilabautistasirley@gmail.com | H61: \N | I61: \N | J61: \N | K61: 38365 | L61: \N | M61: 2 | N61: 2 | O61: \N | P61: \N | Q61: \N | R61: \N | S61: \N | T61: \N | U61: \N | V61: \N | W61: Pendiente | X61: 45929 | Y61: 0 | Z61: \N | AA61: =IFERROR(VLOOKUP(B61,BD_Clez_Premigracion!C:C,1,FALSE),"No encontrado") -> 1095300596
A62: 2232 | B62: 1098718284 | C62: 1 | D62: JORGE ANDRES | E62: BAUTISTA MENDEZ | F62: 3153049735 | G62: joanbamen23@gmail.com | H62: \N | I62: Avenida Búcaros #60-319 torocoma T4 101 | J62: \N | K62: 33657 | L62: \N | M62: 1 | N62: 10 | O62: \N | P62: \N | Q62: \N | R62: 6 | S62: Mongui Muñoz | T62: Padre/Madre | U62: 3168795456 | V62: \N | W62: Activo | X62: 45929 | Y62: 0 | AA62: =IFERROR(VLOOKUP(B62,BD_Clez_Premigracion!C:C,1,FALSE),"No encontrado") -> No encontrado
A63: 2229 | B63: 3079306 | C63: 6 | D63: Manuel Alejandro | E63: Pérez contreras | F63: 3027028560 | G63: alejandrocontreras1932@gmail.com | H63: \N | I63: \N | J63: \N | K63: 33467 | L63: \N | M63: 1 | N63: 1 | O63: \N | P63: \N | Q63: \N | R63: \N | S63: \N | T63: \N | U63: \N | V63: \N | W63: Pendiente | X63: 45929 | Y63: 0 | Z63: \N | AA63: =IFERROR(VLOOKUP(B63,BD_Clez_Premigracion!C:C,1,FALSE),"No encontrado") -> 3079306
A64: 2225 | B64: 1127665592 | C64: 1 | D64: NADIA KARINA | E64: GUERRERO PAZ | F64: 3202888083 | G64: Nadiakarina1085@gmail.com | H64: \N | I64: \N | J64: \N | K64: 31333 | L64: \N | M64: 2 | N64: 4 | O64: \N | P64: \N | Q64: \N | R64: \N | S64: \N | T64: \N | U64: \N | V64: \N | W64: Pendiente | X64: 45929 | Y64: 0 | Z64: \N | AA64: =IFERROR(VLOOKUP(B64,BD_Clez_Premigracion!C:C,1,FALSE),"No encontrado") -> No encontrado
A65: 2207 | B65: 1098812062 | C65: 1 | D65: IVONNE ANDREA | E65: RUEDA VASQUEZ | F65: 3219566017 | G65: andrearueda127@gmail.com | H65: \N | I65: \N | J65: \N | K65: 36068 | L65: \N | M65: 2 | N65: 10 | O65: \N | P65: \N | Q65: \N | R65: \N | S65: \N | T65: \N | U65: \N | V65: \N | W65: Pendiente | X65: 45925 | Y65: 0 | Z65: \N | AA65: =IFERROR(VLOOKUP(B65,BD_Clez_Premigracion!C:C,1,FALSE),"No encontrado") -> 1098812062
A66: 2233 | B66: 1192716330 | C66: 1 | D66: DIEGO EDSON | E66: URIBE SALAZAR | F66: 3123551936 | G66: Diego042024@gmail.com | H66: \N | I66: \N | J66: \N | K66: 37366 | L66: \N | M66: 1 | N66: 4 | O66: \N | P66: \N | Q66: \N | R66: \N | S66: \N | T66: \N | U66: \N | V66: \N | W66: Pendiente | X66: 45929 | Y66: 0 | Z66: \N | AA66: =IFERROR(VLOOKUP(B66,BD_Clez_Premigracion!C:C,1,FALSE),"No encontrado") -> 1192716330
A67: 2214 | B67: 1090521204 | C67: 1 | D67: JULIETH KATHERINE | E67: VILLAMIZAR OSORIO | F67: 3217134813 | G67: Yulipdcdesv@gmail.com | H67: \N | I67: \N | J67: \N | K67: 35949 | L67: \N | M67: 2 | N67: 2 | O67: \N | P67: \N | Q67: \N | R67: \N | S67: \N | T67: \N | U67: \N | V67: \N | W67: Pendiente | X67: 45925 | Y67: 0 | Z67: \N | AA67: =IFERROR(VLOOKUP(B67,BD_Clez_Premigracion!C:C,1,FALSE),"No encontrado") -> 1090521204
A68: 2234 | B68: 1098070689 | C68: 1 | D68: DANIEL HERNANDO | E68: LOPEZ VEGA | F68: 3107907445 | G68: Danielopesitos@gmail.com | H68: \N | I68: Calle 50#22-87 | J68: \N | K68: 38289 | L68: \N | M68: 1 | N68: 2 | O68: \N | P68: \N | Q68: \N | R68: 3 | S68: Hernando Lopez | T68: Padre/Madre | U68: 3212570548 | V68: \N | W68: Activo | X68: 45929 | Y68: 0 | AA68: =IFERROR(VLOOKUP(B68,BD_Clez_Premigracion!C:C,1,FALSE),"No encontrado") -> No encontrado
A69: 2235 | B69: 1098819918 | C69: 1 | D69: ANDRY YURANY | E69: ANDRADE SANDOVAL | F69: 3223223953 | G69: Andryur05@gmail.com | H69: \N | I69: Carrera 18#8a-30 | J69: \N | K69: 36316 | L69: \N | M69: 2 | N69: 2 | O69: \N | P69: \N | Q69: \N | R69: 1 | S69: Daniel | T69: Esposo/a | U69: 3107907445 | V69: \N | W69: Activo | X69: 45929 | Y69: 0 | AA69: =IFERROR(VLOOKUP(B69,BD_Clez_Premigracion!C:C,1,FALSE),"No encontrado") -> No encontrado
A70: 2236 | B70: 1044607327 | C70: 1 | D70: ISABEL SOFIA | E70: RUEDA PORRAS | F70: 3043322841 | G70: Isabelsrueda23@gmail.com | H70: \N | I70: TV 154 #157-65 | J70: \N | K70: 38344 | L70: \N | M70: 2 | N70: 3 | O70: \N | P70: \N | Q70: \N | R70: 7 | S70: Shirley porras | T70: Padre/Madre | U70: 3155130595 | V70: \N | W70: Activo | X70: 45929 | Y70: 0 | AA70: =IFERROR(VLOOKUP(B70,BD_Clez_Premigracion!C:C,1,FALSE),"No encontrado") -> No encontrado
A71: 2237 | B71: 1102361317 | C71: 3 | D71: Miguel Angel | E71: Torres Martinez | F71: 3006043949 | G71: miguelangeltorresmartinez07@gmail.com | H71: \N | I71: Cr 15 # 18-70 | J71: \N | K71: 39329 | L71: \N | M71: 1 | N71: 5 | O71: \N | P71: \N | Q71: \N | R71: 25 | S71: Mary luz Martínez castro | T71: Padre/Madre | U71: 3144219919 | V71: \N | W71: Activo | X71: 45929 | Y71: 0 | AA71: =IFERROR(VLOOKUP(B71,BD_Clez_Premigracion!C:C,1,FALSE),"No encontrado") -> No encontrado
A72: 2238 | B72: 1094267818 | C72: 1 | D72: Sair Alberto | E72: Pineda Gamboa | F72: 3016218873 | G72: sairalberto@gmail.com | H72: \N | I72: Callejas Torres | J72: \N | K72: 33565 | L72: \N | M72: 1 | N72: 4 | O72: \N | P72: \N | Q72: \N | R72: 7 | S72: Katherin Caceres | T72: Esposo/a | U72: 3168294669 | V72: \N | W72: Activo | X72: 45929 | Y72: 0 | AA72: =IFERROR(VLOOKUP(B72,BD_Clez_Premigracion!C:C,1,FALSE),"No encontrado") -> No encontrado
A73: 2210 | B73: 1005448346 | C73: 1 | D73: LEZLY ANDREA | E73: ORDOÑEZ TORRES | F73: 3187249327 | G73: andreaot49@gmail.com | H73: \N | I73: \N | J73: \N | K73: 37138 | L73: \N | M73: 2 | N73: 5 | O73: \N | P73: \N | Q73: \N | R73: \N | S73: \N | T73: \N | U73: \N | V73: \N | W73: Pendiente | X73: 45925 | Y73: 0 | Z73: \N | AA73: =IFERROR(VLOOKUP(B73,BD_Clez_Premigracion!C:C,1,FALSE),"No encontrado") -> 1005448346
A74: 2241 | B74: 1095848550 | C74: 1 | D74: DARIANA VICTORIA | E74: GIL RODRIGUEZ | F74: 3138817565 | G74: Darianagil24@gmail.com | H74: \N | I74: \N | J74: \N | K74: 37918 | L74: \N | M74: 2 | N74: 5 | O74: \N | P74: \N | Q74: \N | R74: \N | S74: \N | T74: \N | U74: \N | V74: \N | W74: Pendiente | X74: 45930 | Y74: 0 | Z74: \N | AA74: =IFERROR(VLOOKUP(B74,BD_Clez_Premigracion!C:C,1,FALSE),"No encontrado") -> 1095848550
A75: 2239 | B75: 1095822856 | C75: 1 | D75: NAZLY ADRIANA | E75: VISBAL FONSECA | F75: 3166038564 | G75: Nazly20-08@hotmail.com | H75: \N | I75: \N | J75: \N | K75: 34703 | L75: \N | M75: 2 | N75: 7 | O75: \N | P75: \N | Q75: \N | R75: \N | S75: \N | T75: \N | U75: \N | V75: \N | W75: Pendiente | X75: 45930 | Y75: 0 | Z75: \N | AA75: =IFERROR(VLOOKUP(B75,BD_Clez_Premigracion!C:C,1,FALSE),"No encontrado") -> 1095822856
A76: 2224 | B76: 13717603 | C76: 1 | D76: JAVIER DARIO | E76: CARDENAS SIERRA | F76: 3122032476 | G76: Javierdariocatdenassierra@gmail.com | H76: \N | I76: \N | J76: \N | K76: 28715 | L76: \N | M76: 1 | N76: 5 | O76: \N | P76: \N | Q76: \N | R76: \N | S76: \N | T76: \N | U76: \N | V76: \N | W76: Pendiente | X76: 45927 | Y76: 0 | Z76: \N | AA76: =IFERROR(VLOOKUP(B76,BD_Clez_Premigracion!C:C,1,FALSE),"No encontrado") -> 13717603
A77: 2243 | B77: 1096245956 | C77: 1 | D77: YULY VANESSA | E77: SARMIENTO VILLA | F77: 3208524555 | G77: july_29sarmiento@hotmail.com | H77: \N | I77: \N | J77: \N | K77: 35640 | L77: \N | M77: 2 | N77: 9 | O77: \N | P77: \N | Q77: \N | R77: \N | S77: \N | T77: \N | U77: \N | V77: \N | W77: Pendiente | X77: 45930 | Y77: 0 | Z77: \N | AA77: =IFERROR(VLOOKUP(B77,BD_Clez_Premigracion!C:C,1,FALSE),"No encontrado") -> 1096245956
A78: 2244 | B78: 1098804234 | C78: 1 | D78: ANDRES FELIPE | E78: RUIZ BLANCO | F78: 3172442099 | G78: andresruiz-0698@hotmail.com | H78: \N | I78: \N | J78: \N | K78: 35832 | L78: \N | M78: 1 | N78: 9 | O78: \N | P78: \N | Q78: \N | R78: \N | S78: \N | T78: \N | U78: \N | V78: \N | W78: Pendiente | X78: 45930 | Y78: 0 | Z78: \N | AA78: =IFERROR(VLOOKUP(B78,BD_Clez_Premigracion!C:C,1,FALSE),"No encontrado") -> 1098804234
A79: 2245 | B79: 1005235289 | C79: 1 | D79: JESUS ALEJANDRO | E79: LAGUADO ACEVEDO | F79: 3204542318 | G79: jesuslaguado801@gmail.com | H79: \N | I79: \N | J79: \N | K79: 37174 | L79: \N | M79: 1 | N79: 5 | O79: \N | P79: \N | Q79: \N | R79: \N | S79: \N | T79: \N | U79: \N | V79: \N | W79: Pendiente | X79: 45930 | Y79: 0 | Z79: \N | AA79: =IFERROR(VLOOKUP(B79,BD_Clez_Premigracion!C:C,1,FALSE),"No encontrado") -> 1005235289
A80: 2248 | B80: 1091355396 | C80: 1 | D80: LAURA YAIRYNA | E80: CUEVAS QUIJANO | F80: 3105818717 | G80: laura.yairyna.cuevas@gmail.com | H80: \N | I80: \N | J80: \N | K80: 38533 | L80: \N | M80: 2 | N80: 6 | O80: \N | P80: \N | Q80: \N | R80: \N | S80: \N | T80: \N | U80: \N | V80: \N | W80: Pendiente | X80: 45930 | Y80: 0 | Z80: \N | AA80: =IFERROR(VLOOKUP(B80,BD_Clez_Premigracion!C:C,1,FALSE),"No encontrado") -> 1091355396
A81: 2249 | B81: 80870963 | C81: 1 | D81: MIGUEL ANGEL | E81: GAITAN HINCAPIE | F81: 3157532158 | G81: magh.2743@gmail.com | H81: \N | I81: \N | J81: \N | K81: 30971 | L81: \N | M81: 1 | N81: 4 | O81: \N | P81: \N | Q81: \N | R81: \N | S81: \N | T81: \N | U81: \N | V81: \N | W81: Pendiente | X81: 45930 | Y81: 0 | Z81: \N | AA81: =IFERROR(VLOOKUP(B81,BD_Clez_Premigracion!C:C,1,FALSE),"No encontrado") -> 80870963
A82: 2253 | B82: 1007355147 | C82: 1 | D82: JUAN CAMILO | E82: GOMEZ EUGENIO | F82: 3249070072 | G82: juangomezeugenio78@gmail.com | H82: \N | I82: \N | J82: \N | K82: 36730 | L82: \N | M82: 1 | N82: 5 | O82: \N | P82: \N | Q82: \N | R82: \N | S82: \N | T82: \N | U82: \N | V82: \N | W82: Pendiente | X82: 45930 | Y82: 0 | Z82: \N | AA82: =IFERROR(VLOOKUP(B82,BD_Clez_Premigracion!C:C,1,FALSE),"No encontrado") -> 1007355147
A83: 2254 | B83: 1005235566 | C83: 1 | D83: MARIA JOSE | E83: SANCHEZ HEREDIA | F83: 3103168140 | G83: Mariajose120728@gmail.com | H83: \N | I83: \N | J83: \N | K83: 37237 | L83: \N | M83: 2 | N83: 5 | O83: \N | P83: \N | Q83: \N | R83: \N | S83: \N | T83: \N | U83: \N | V83: \N | W83: Pendiente | X83: 45930 | Y83: 0 | Z83: \N | AA83: =IFERROR(VLOOKUP(B83,BD_Clez_Premigracion!C:C,1,FALSE),"No encontrado") -> 1005235566
A84: 2250 | B84: 1076666956 | C84: 1 | D84: BRAYAN STIVEN | E84: RODRIGUEZ RODRIGUEZ | F84: 3204782802 | G84: brayansrodrig@gmail.com | H84: \N | I84: \N | J84: \N | K84: 35753 | L84: \N | M84: 1 | N84: 6 | O84: \N | P84: \N | Q84: \N | R84: \N | S84: \N | T84: \N | U84: \N | V84: \N | W84: Pendiente | X84: 45930 | Y84: 0 | Z84: \N | AA84: =IFERROR(VLOOKUP(B84,BD_Clez_Premigracion!C:C,1,FALSE),"No encontrado") -> 1076666956
A85: 2242 | B85: 1005282516 | C85: 1 | D85: ANGIE CRISTINA | E85: LOZANO MOGOLLON | F85: 3163220791 | G85: cristinangie09@gmail.com | H85: \N | I85: D | J85: \N | K85: 37873 | L85: \N | M85: 2 | N85: 3 | O85: \N | P85: \N | Q85: \N | R85: 9 | S85: Esperanza Mogollón Chaparro | T85: Padre/Madre | U85: 3152841584 | V85: \N | W85: Activo | X85: 45930 | Y85: 0 | AA85: =IFERROR(VLOOKUP(B85,BD_Clez_Premigracion!C:C,1,FALSE),"No encontrado") -> 1005282516
A86: 2255 | B86: 32175631 | C86: 2 | D86: Angel | E86: Guillén | F86: 3166370293 | G86: angeloguillen85@gmail.com | H86: \N | I86: \N | J86: \N | K86: 38602 | L86: \N | M86: 1 | N86: 10 | O86: \N | P86: \N | Q86: \N | R86: \N | S86: \N | T86: \N | U86: \N | V86: \N | W86: Pendiente | X86: 45930 | Y86: 0 | Z86: \N | AA86: =IFERROR(VLOOKUP(B86,BD_Clez_Premigracion!C:C,1,FALSE),"No encontrado") -> No encontrado
A87: 2256 | B87: 1098073585 | C87: 3 | D87: Sara | E87: Otalora bohorquez | F87: 3108897521 | G87: Otalorasara244@gmail.com | H87: \N | I87: Piedecuesta a | J87: \N | K87: 39550 | L87: \N | M87: 2 | N87: 5 | O87: \N | P87: \N | Q87: \N | R87: 7 | S87: Sonia Isabel Bohórquez Vargas | T87: Padre/Madre | U87: 3146061376 | V87: \N | W87: Activo | X87: 45930 | Y87: 0 | AA87: =IFERROR(VLOOKUP(B87,BD_Clez_Premigracion!C:C,1,FALSE),"No encontrado") -> No encontrado
A88: 2257 | B88: 1098610967 | C88: 1 | D88: FRANCISCO JAVIER | E88: ORTEGA CARRASCAL | F88: 3177383838 | G88: fjortegacarrascal@gmail.com | H88: \N | I88: \N | J88: \N | K88: 31196 | L88: \N | M88: 1 | N88: 2 | O88: \N | P88: \N | Q88: \N | R88: \N | S88: \N | T88: \N | U88: \N | V88: \N | W88: Pendiente | X88: 45930 | Y88: 0 | Z88: \N | AA88: =IFERROR(VLOOKUP(B88,BD_Clez_Premigracion!C:C,1,FALSE),"No encontrado") -> No encontrado
A89: 2258 | B89: 1098810614 | C89: 1 | D89: GEORGE SEBASTIAN | E89: SANTOS RINCON | F89: 3158013119 | G89: georgesantos0714@gmail.com | H89: \N | I89: \N | J89: \N | K89: 35990 | L89: \N | M89: 1 | N89: 8 | O89: \N | P89: \N | Q89: \N | R89: \N | S89: \N | T89: \N | U89: \N | V89: \N | W89: Pendiente | X89: 45930 | Y89: 0 | Z89: \N | AA89: =IFERROR(VLOOKUP(B89,BD_Clez_Premigracion!C:C,1,FALSE),"No encontrado") -> 1098810614
A90: 2259 | B90: 1095790451 | C90: 1 | D90: Paola Andrea | E90: Flórez Gamboa | F90: 3108756354 | G90: andrwflorez12@gmail.com | H90: \N | I90: \N | J90: \N | K90: 38332 | L90: \N | M90: 2 | N90: 2 | O90: \N | P90: \N | Q90: \N | R90: \N | S90: \N | T90: \N | U90: \N | V90: \N | W90: Pendiente | X90: 45930 | Y90: 0 | Z90: \N | AA90: =IFERROR(VLOOKUP(B90,BD_Clez_Premigracion!C:C,1,FALSE),"No encontrado") -> No encontrado
A91: 2261 | B91: 1098625892 | C91: 1 | D91: DANIELA DAYANA | E91: RINCON DIAZ | F91: 3153740663 | G91: cr2386661@gmail.com | H91: \N | I91: \N | J91: \N | K91: 38322 | L91: \N | M91: 2 | N91: 10 | O91: \N | P91: \N | Q91: \N | R91: \N | S91: \N | T91: \N | U91: \N | V91: \N | W91: Pendiente | X91: 45930 | Y91: 0 | Z91: \N | AA91: =IFERROR(VLOOKUP(B91,BD_Clez_Premigracion!C:C,1,FALSE),"No encontrado") -> No encontrado
A92: 2264 | B92: 1090475652 | C92: 1 | D92: David | E92: Escobar | F92: 3022944427 | G92: qqtabox@gmail.com | H92: \N | I92: Ed Alto pamplonita 407 | J92: \N | K92: 34314 | L92: \N | M92: 1 | N92: 6 | O92: \N | P92: \N | Q92: \N | R92: 4 | S92: Myriam | T92: Padre/Madre | U92: 3164538487 | V92: \N | W92: Activo | X92: 45931 | Y92: 0 | AA92: =IFERROR(VLOOKUP(B92,BD_Clez_Premigracion!C:C,1,FALSE),"No encontrado") -> No encontrado
A93: 2247 | B93: 1098816206 | C93: 1 | D93: OSCAR ANDRES | E93: POMBO RIVERA | F93: 3143619122 | G93: Oscar.pombo34@gmail.com | H93: \N | I93: \N | J93: \N | K93: 36203 | L93: \N | M93: 1 | N93: 1 | O93: \N | P93: \N | Q93: \N | R93: \N | S93: \N | T93: \N | U93: \N | V93: \N | W93: Pendiente | X93: 45930 | Y93: 0 | Z93: \N | AA93: =IFERROR(VLOOKUP(B93,BD_Clez_Premigracion!C:C,1,FALSE),"No encontrado") -> 1098816206
A94: 2262 | B94: 1019075573 | C94: 1 | D94: Juan daniel | E94: Ruiz mendivelso | F94: 3115976380 | G94: struens12@gmail.com | H94: \N | I94: \N | J94: \N | K94: 33867 | L94: \N | M94: 1 | N94: 2 | O94: \N | P94: \N | Q94: \N | R94: \N | S94: \N | T94: \N | U94: \N | V94: \N | W94: Pendiente | X94: 45930 | Y94: 0 | Z94: \N | AA94: =IFERROR(VLOOKUP(B94,BD_Clez_Premigracion!C:C,1,FALSE),"No encontrado") -> 1019075573
A95: 2268 | B95: 1090398553 | C95: 1 | D95: ADRIANA PAOLA | E95: REAL CHAVARRO | F95: 3208919270 | G95: adris1126@hotmail.com | H95: \N | I95: \N | J95: \N | K95: 32473 | L95: \N | M95: 2 | N95: 6 | O95: \N | P95: \N | Q95: \N | R95: \N | S95: \N | T95: \N | U95: \N | V95: \N | W95: Pendiente | X95: 45931 | Y95: 0 | Z95: \N | AA95: =IFERROR(VLOOKUP(B95,BD_Clez_Premigracion!C:C,1,FALSE),"No encontrado") -> 1090398553
A96: 2269 | B96: 1097784450 | C96: 3 | D96: Juan David | E96: Montoya Carreño | F96: 3153967917 | G96: jdavid062008@gmail.com | H96: \N | I96: \N | J96: \N | K96: 39605 | L96: \N | M96: 1 | N96: 2 | O96: \N | P96: \N | Q96: \N | R96: \N | S96: \N | T96: \N | U96: \N | V96: \N | W96: Pendiente | X96: 45931 | Y96: 0 | Z96: \N | AA96: =IFERROR(VLOOKUP(B96,BD_Clez_Premigracion!C:C,1,FALSE),"No encontrado") -> 1097784450
A97: 2270 | B97: 1193579042 | C97: 1 | D97: JULIETH VALENTINA | E97: CARDENAS ASCENCIO | F97: 3218745895 | G97: Valentinariver@hotmail.com | H97: \N | I97: \N | J97: \N | K97: 37338 | L97: \N | M97: 2 | N97: 6 | O97: \N | P97: \N | Q97: \N | R97: \N | S97: \N | T97: \N | U97: \N | V97: \N | W97: Pendiente | X97: 45931 | Y97: 0 | Z97: \N | AA97: =IFERROR(VLOOKUP(B97,BD_Clez_Premigracion!C:C,1,FALSE),"No encontrado") -> No encontrado
A98: 2271 | B98: 1005162538 | C98: 1 | D98: YERSON EDUARDO | E98: JURADO DIAZ | F98: 3160810229 | G98: Dyerson827@gmail.com | H98: \N | I98: \N | J98: \N | K98: 37045 | L98: \N | M98: 1 | N98: 8 | O98: \N | P98: \N | Q98: \N | R98: \N | S98: \N | T98: \N | U98: \N | V98: \N | W98: Pendiente | X98: 45931 | Y98: 0 | Z98: \N | AA98: =IFERROR(VLOOKUP(B98,BD_Clez_Premigracion!C:C,1,FALSE),"No encontrado") -> 1005162538
A99: 2272 | B99: 1005336822 | C99: 1 | D99: YOAN SEVASTIAN | E99: DUARTE VILA | F99: 3024908687 | G99: johansebastianduartevila586@gmail.com | H99: \N | I99: \N | J99: \N | K99: 36743 | L99: \N | M99: 1 | N99: 8 | O99: \N | P99: \N | Q99: \N | R99: \N | S99: \N | T99: \N | U99: \N | V99: \N | W99: Pendiente | X99: 45931 | Y99: 0 | Z99: \N | AA99: =IFERROR(VLOOKUP(B99,BD_Clez_Premigracion!C:C,1,FALSE),"No encontrado") -> 1005336822
A100: 2274 | B100: 1005261045 | C100: 1 | D100: DANNA GABRIELA | E100: ROJAS ROJAS | F100: 3133865540 | G100: dannarojasx3@gmail.com | H100: \N | I100: \N | J100: \N | K100: 37865 | L100: \N | M100: 2 | N100: 8 | O100: \N | P100: \N | Q100: \N | R100: \N | S100: \N | T100: \N | U100: \N | V100: \N | W100: Pendiente | X100: 45931 | Y100: 0 | Z100: \N | AA100: =IFERROR(VLOOKUP(B100,BD_Clez_Premigracion!C:C,1,FALSE),"No encontrado") -> 1005261045
A101: 2273 | B101: 1003245545 | C101: 1 | D101: MARIA ANGELICA | E101: MENESES RINCON | F101: 3152603201 | G101: mmeneses357@unab.edu.co | H101: \N | I101: \N | J101: \N | K101: 37120 | L101: \N | M101: 2 | N101: 2 | O101: \N | P101: \N | Q101: \N | R101: \N | S101: \N | T101: \N | U101: \N | V101: \N | W101: Pendiente | X101: 45931 | Y101: 0 | Z101: \N | AA101: =IFERROR(VLOOKUP(B101,BD_Clez_Premigracion!C:C,1,FALSE),"No encontrado") -> No encontrado
A102: 2275 | B102: 1096700440 | C102: 1 | D102: MAILETH STEFANNY | E102: HURTADO MUÑOZ | F102: 3245568323 | G102: mailethstefanny.h@gmail.com | H102: \N | I102: CRA 15#65-50 | J102: \N | K102: 38234 | L102: \N | M102: 2 | N102: 10 | O102: \N | P102: \N | Q102: \N | R102: 9 | S102: GLORIA ENIT MUÑOZ GOMEZ | T102: Padre/Madre | U102: 3142127071 | V102: \N | W102: Activo | X102: 45931 | Y102: 0 | AA102: =IFERROR(VLOOKUP(B102,BD_Clez_Premigracion!C:C,1,FALSE),"No encontrado") -> No encontrado
A103: 2278 | B103: 1007772937 | C103: 1 | D103: Marianh carolay | E103: Torres tellez | F103: 3208970735 | G103: Torrescarolay64@gmail.com | H103: \N | I103: \N | J103: \N | K103: 36702 | L103: \N | M103: 2 | N103: 4 | O103: \N | P103: \N | Q103: \N | R103: \N | S103: \N | T103: \N | U103: \N | V103: \N | W103: Pendiente | X103: 45931 | Y103: 0 | Z103: \N | AA103: =IFERROR(VLOOKUP(B103,BD_Clez_Premigracion!C:C,1,FALSE),"No encontrado") -> No encontrado
A104: 2222 | B104: 1004348210 | C104: 1 | D104: CRISTIAN CAMILO | E104: CANDANOZA OLIVO | F104: 3217060838 | G104: cristiancandanoza0@gmail.com | H104: \N | I104: \N | J104: \N | K104: 37004 | L104: \N | M104: 1 | N104: 5 | O104: \N | P104: \N | Q104: \N | R104: \N | S104: \N | T104: \N | U104: \N | V104: \N | W104: Pendiente | X104: 45926 | Y104: 0 | Z104: \N | AA104: =IFERROR(VLOOKUP(B104,BD_Clez_Premigracion!C:C,1,FALSE),"No encontrado") -> 1004348210
A105: 2276 | B105: 1098757539 | C105: 1 | D105: Dayana Yulieth | E105: Barbosa Martinez | F105: 3184975541 | G105: Dayanabarbosa45@gmail.com | H105: \N | I105: \N | J105: \N | K105: 34534 | L105: \N | M105: 2 | N105: 3 | O105: \N | P105: \N | Q105: \N | R105: \N | S105: \N | T105: \N | U105: \N | V105: \N | W105: Pendiente | X105: 45931 | Y105: 0 | Z105: \N | AA105: =IFERROR(VLOOKUP(B105,BD_Clez_Premigracion!C:C,1,FALSE),"No encontrado") -> 1098757539
A106: 2280 | B106: 1093775147 | C106: 1 | D106: JOICY DAYANNA | E106: SAAVEDRA MEDINA | F106: 3023859906 | G106: saavedrajoicy@gmail.com | H106: \N | I106: Cll 10An # 2A-23 bosque paraiso | J106: \N | K106: 34632 | L106: \N | M106: 2 | N106: 6 | O106: \N | P106: \N | Q106: \N | R106: 5 | S106: Nancy Saavedra | T106: Padre/Madre | U106: 3142944260 | V106: \N | W106: Activo | X106: 45932 | Y106: 0 | AA106: =IFERROR(VLOOKUP(B106,BD_Clez_Premigracion!C:C,1,FALSE),"No encontrado") -> No encontrado
A107: 2283 | B107: 1098615709 | C107: 1 | D107: EDWIN SANTIAGO | E107: CACUA BAEZ | F107: 3232410651 | G107: Edwincacua560@gmail.com | H107: \N | I107: \N | J107: \N | K107: 38127 | L107: \N | M107: 1 | N107: 10 | O107: \N | P107: \N | Q107: \N | R107: \N | S107: \N | T107: \N | U107: \N | V107: \N | W107: Pendiente | X107: 45932 | Y107: 0 | Z107: \N | AA107: =IFERROR(VLOOKUP(B107,BD_Clez_Premigracion!C:C,1,FALSE),"No encontrado") -> 1098615709
A108: 2282 | B108: 1005334263 | C108: 3 | D108: DANIEL DAVID | E108: LANDAZABAL CABALLERO | F108: 3213848770 | G108: ddlc141@gmail.com | H108: \N | I108: \N | J108: \N | K108: 36791 | L108: \N | M108: 1 | N108: 5 | O108: \N | P108: \N | Q108: \N | R108: \N | S108: \N | T108: \N | U108: \N | V108: \N | W108: Pendiente | X108: 45932 | Y108: 0 | Z108: \N | AA108: =IFERROR(VLOOKUP(B108,BD_Clez_Premigracion!C:C,1,FALSE),"No encontrado") -> 1005334263
A109: 2284 | B109: 1090535263 | C109: 1 | D109: FREDDY | E109: PARADA ORTEGA | F109: 3135740397 | G109: Freddypara46@gmail.com | H109: \N | I109: \N | J109: \N | K109: 36451 | L109: \N | M109: 1 | N109: 4 | O109: \N | P109: \N | Q109: \N | R109: \N | S109: \N | T109: \N | U109: \N | V109: \N | W109: Pendiente | X109: 45932 | Y109: 0 | Z109: \N | AA109: =IFERROR(VLOOKUP(B109,BD_Clez_Premigracion!C:C,1,FALSE),"No encontrado") -> No encontrado
A110: 2246 | B110: 63346401 | C110: 1 | D110: CLAUDIA AZUCENA | E110: HURTADO ANAYA | F110: 3123137845 | G110: claudiahurtado197@gmail.com | H110: \N | I110: \N | J110: \N | K110: 24844 | L110: \N | M110: 2 | N110: 3 | O110: \N | P110: \N | Q110: \N | R110: \N | S110: \N | T110: \N | U110: \N | V110: \N | W110: Pendiente | X110: 45930 | Y110: 0 | Z110: \N | AA110: =IFERROR(VLOOKUP(B110,BD_Clez_Premigracion!C:C,1,FALSE),"No encontrado") -> 63346401
A111: 2285 | B111: 1005240620 | C111: 1 | D111: DAVID SANTIAGO | E111: ACOSTA BUENO | F111: 3158906547 | G111: davodsab20@gmail.com | H111: \N | I111: \N | J111: \N | K111: 37945 | L111: \N | M111: 1 | N111: 8 | O111: \N | P111: \N | Q111: \N | R111: \N | S111: \N | T111: \N | U111: \N | V111: \N | W111: Pendiente | X111: 45932 | Y111: 0 | Z111: \N | AA111: =IFERROR(VLOOKUP(B111,BD_Clez_Premigracion!C:C,1,FALSE),"No encontrado") -> 1005240620
A112: 2286 | B112: 1007775913 | C112: 1 | D112: LEYDY KATERINE | E112: PEÑA CAICEDO | F112: 3164557109 | G112: katherinepena686@gmail.com | H112: \N | I112: \N | J112: \N | K112: 36772 | L112: \N | M112: 2 | N112: 9 | O112: \N | P112: \N | Q112: \N | R112: \N | S112: \N | T112: \N | U112: \N | V112: \N | W112: Pendiente | X112: 45932 | Y112: 0 | Z112: \N | AA112: =IFERROR(VLOOKUP(B112,BD_Clez_Premigracion!C:C,1,FALSE),"No encontrado") -> No encontrado
A113: 2287 | B113: 1095832295 | C113: 1 | D113: YARICELL TATIANA | E113: MARTINEZ SALCEDO | F113: 3212189397 | G113: yaricelltatianam@gmail.com | H113: \N | I113: \N | J113: \N | K113: 35321 | L113: \N | M113: 2 | N113: 3 | O113: \N | P113: \N | Q113: \N | R113: \N | S113: \N | T113: \N | U113: \N | V113: \N | W113: Pendiente | X113: 45932 | Y113: 0 | Z113: \N | AA113: =IFERROR(VLOOKUP(B113,BD_Clez_Premigracion!C:C,1,FALSE),"No encontrado") -> 1095832295
A114: 2289 | B114: 1093797175 | C114: 1 | D114: LIZETH PAOLA | E114: DAZA QUINTERO | F114: 3232206355 | G114: lizethyangie@gmail.com | H114: \N | I114: \N | J114: \N | K114: 36100 | L114: \N | M114: 2 | N114: 6 | O114: \N | P114: \N | Q114: \N | R114: \N | S114: \N | T114: \N | U114: \N | V114: \N | W114: Pendiente | X114: 45933 | Y114: 0 | Z114: \N | AA114: =IFERROR(VLOOKUP(B114,BD_Clez_Premigracion!C:C,1,FALSE),"No encontrado") -> 1093797175
A115: 2290 | B115: 1097911303 | C115: 1 | D115: LESLY VALENTINA | E115: PINZON PALOMINO | F115: 3001632609 | G115: leslyevalentina4@gmail.com | H115: \N | I115: Calle 7N 7-53 apto 501 edificio Infinity Junín 1 | J115: \N | K115: 38768 | L115: \N | M115: 2 | N115: 5 | O115: \N | P115: \N | Q115: \N | R115: 7 | S115: DIANA CAROLINA PALOMINO | T115: Padre/Madre | U115: 3208307393 | V115: \N | W115: Activo | X115: 45933 | Y115: 0 | AA115: =IFERROR(VLOOKUP(B115,BD_Clez_Premigracion!C:C,1,FALSE),"No encontrado") -> 1097911303
A116: 2291 | B116: 5489941 | C116: 1 | D116: Edinson | E116: Moncada | F116: 3183963534 | G116: edinsonmoncada19@gmail.com | H116: \N | I116: \N | J116: \N | K116: 29391 | L116: \N | M116: 1 | N116: 4 | O116: \N | P116: \N | Q116: \N | R116: \N | S116: \N | T116: \N | U116: \N | V116: \N | W116: Pendiente | X116: 45933 | Y116: 0 | Z116: \N | AA116: =IFERROR(VLOOKUP(B116,BD_Clez_Premigracion!C:C,1,FALSE),"No encontrado") -> 5489941
A117: 2294 | B117: 1095934040 | C117: 1 | D117: PAOLA ANDREA | E117: SIERRA LOZANO | F117: 3106732017 | G117: Paosierralozano@gmail.com | H117: \N | I117: Calle 10 22 53 | J117: \N | K117: 34218 | L117: \N | M117: 2 | N117: 8 | O117: \N | P117: \N | Q117: \N | R117: 1 | S117: Gladys Lozano | T117: Padre/Madre | U117: 3102356844 | V117: \N | W117: Activo | X117: 45933 | Y117: 0 | AA117: =IFERROR(VLOOKUP(B117,BD_Clez_Premigracion!C:C,1,FALSE),"No encontrado") -> No encontrado
A118: 2295 | B118: 1005028371 | C118: 1 | D118: MICHELLE DANIELA | E118: BERMON ROMAN | F118: 3114043359 | G118: michellebermon5@gmail.com | H118: \N | I118: Mz D19 lote 13 torcoroma II | J118: \N | K118: 37762 | L118: \N | M118: 2 | N118: 4 | O118: \N | P118: \N | Q118: \N | R118: 4 | S118: Bernarda Roman | T118: Padre/Madre | U118: 3225907946 | V118: \N | W118: Activo | X118: 45933 | Y118: 0 | AA118: =IFERROR(VLOOKUP(B118,BD_Clez_Premigracion!C:C,1,FALSE),"No encontrado") -> No encontrado
A119: 2292 | B119: 5088153 | C119: 6 | D119: Joseph gregory | E119: De los santos bastidas | F119: 3219507421 | G119: josephdossantos132904@gmail.com | H119: \N | I119: \N | J119: \N | K119: 33341 | L119: \N | M119: 1 | N119: 2 | O119: \N | P119: \N | Q119: \N | R119: \N | S119: \N | T119: \N | U119: \N | V119: \N | W119: Pendiente | X119: 45933 | Y119: 0 | Z119: \N | AA119: =IFERROR(VLOOKUP(B119,BD_Clez_Premigracion!C:C,1,FALSE),"No encontrado") -> 5088153
A120: 2288 | B120: 1116550776 | C120: 1 | D120: Karen julieth | E120: Dueñez morales | F120: 3202010959 | G120: Jullduenez2022@gmail.com | H120: \N | I120: \N | J120: \N | K120: 34685 | L120: \N | M120: 2 | N120: 9 | O120: \N | P120: \N | Q120: \N | R120: \N | S120: \N | T120: \N | U120: \N | V120: \N | W120: Pendiente | X120: 45933 | Y120: 0 | Z120: \N | AA120: =IFERROR(VLOOKUP(B120,BD_Clez_Premigracion!C:C,1,FALSE),"No encontrado") -> 1116550776
A121: 2293 | B121: 1116798906 | C121: 1 | D121: CAMILO ALEJANDRO | E121: SANDOVAL CISNEROS | F121: 3152222034 | G121: alejandro_cisneros94@hotmail.com | H121: \N | I121: \N | J121: \N | K121: 34526 | L121: \N | M121: 1 | N121: 2 | O121: \N | P121: \N | Q121: \N | R121: \N | S121: \N | T121: \N | U121: \N | V121: \N | W121: Pendiente | X121: 45933 | Y121: 0 | Z121: \N | AA121: =IFERROR(VLOOKUP(B121,BD_Clez_Premigracion!C:C,1,FALSE),"No encontrado") -> No encontrado
A122: 2281 | B122: 1090534415 | C122: 1 | D122: INGRID YULIANI | E122: CONTRERAS ATUESTA | F122: 3227488121 | G122: yulianiatuesta@gmail.com | H122: \N | I122: \N | J122: \N | K122: 36463 | L122: \N | M122: 2 | N122: 4 | O122: \N | P122: \N | Q122: \N | R122: \N | S122: \N | T122: \N | U122: \N | V122: \N | W122: Pendiente | X122: 45932 | Y122: 0 | Z122: \N | AA122: =IFERROR(VLOOKUP(B122,BD_Clez_Premigracion!C:C,1,FALSE),"No encontrado") -> 1090534415
A123: 2215 | B123: 1093796478 | C123: 1 | D123: CLARIBETH | E123: CLARO ASCANIO | F123: 3152883248 | G123: Clariclaroas@gmail.com | H123: \N | I123: \N | J123: \N | K123: 36018 | L123: \N | M123: 2 | N123: 2 | O123: \N | P123: \N | Q123: \N | R123: \N | S123: \N | T123: \N | U123: \N | V123: \N | W123: Pendiente | X123: 45925 | Y123: 0 | Z123: \N | AA123: =IFERROR(VLOOKUP(B123,BD_Clez_Premigracion!C:C,1,FALSE),"No encontrado") -> 1093796478
A124: 2297 | B124: 1090443270 | C124: 1 | D124: BRIAN LEONARDO | E124: ANGULO TELLEZ | F124: 3212688204 | G124: leoangulotellez@gmail.com | H124: \N | I124: \N | J124: \N | K124: 33579 | L124: \N | M124: 1 | N124: 4 | O124: \N | P124: \N | Q124: \N | R124: \N | S124: \N | T124: \N | U124: \N | V124: \N | W124: Pendiente | X124: 45934 | Y124: 0 | Z124: \N | AA124: =IFERROR(VLOOKUP(B124,BD_Clez_Premigracion!C:C,1,FALSE),"No encontrado") -> 1090443270
A125: 2298 | B125: 1093590952 | C125: 1 | D125: Anthony Lizandro | E125: Blanco Villarreal | F125: 3138034366 | G125: anthonygamerz12@gmail.com | H125: \N | I125: Avenida 5B #8-30 Prados del este | J125: \N | K125: 38456 | L125: \N | M125: 1 | N125: 4 | O125: \N | P125: \N | Q125: \N | R125: 4 | S125: Joselin Andrea Villarreal | T125: Padre/Madre | U125: 3102388347 | V125: \N | W125: Activo | X125: 45935 | Y125: 0 | AA125: =IFERROR(VLOOKUP(B125,BD_Clez_Premigracion!C:C,1,FALSE),"No encontrado") -> No encontrado
A126: 2299 | B126: 1090393647 | C126: 1 | D126: JOSELIN ANDREA | E126: VILLARREAL | F126: 3102388347 | G126: jandreavillareal@gmail.com | H126: \N | I126: Av 5B#8-30 Prados del Este | J126: \N | K126: 32275 | L126: \N | M126: 2 | N126: 4 | O126: \N | P126: \N | Q126: \N | R126: 4 | S126: Anthony Blanco | T126: Hijo/a | U126: 3108034366 | V126: \N | W126: Activo | X126: 45935 | Y126: 0 | AA126: =IFERROR(VLOOKUP(B126,BD_Clez_Premigracion!C:C,1,FALSE),"No encontrado") -> No encontrado
A127: 2267 | B127: 88233818 | C127: 1 | D127: DANIEL | E127: BAENA PADILLA | F127: 3057367122 | G127: danielbaenapadilla@gmail.com | H127: \N | I127: \N | J127: \N | K127: 28779 | L127: \N | M127: 1 | N127: 6 | O127: \N | P127: \N | Q127: \N | R127: \N | S127: \N | T127: \N | U127: \N | V127: \N | W127: Pendiente | X127: 45931 | Y127: 0 | Z127: \N | AA127: =IFERROR(VLOOKUP(B127,BD_Clez_Premigracion!C:C,1,FALSE),"No encontrado") -> 88233818
A128: 2300 | B128: 1005051293 | C128: 1 | D128: MARIA CAMILA | E128: PARDO REALES | F128: 3133119819 | G128: Mariacamilapardo@outlook.es | H128: \N | I128: Avenida libertadores conjunto residencial prados 1 casa 18 | J128: \N | K128: 36582 | L128: \N | M128: 2 | N128: 4 | O128: \N | P128: \N | Q128: \N | R128: 4 | S128: Nathaly Orozco | T128: Primo/a | U128: +57 316 6866784 | V128: \N | W128: Activo | X128: 45935 | Y128: 0 | AA128: =IFERROR(VLOOKUP(B128,BD_Clez_Premigracion!C:C,1,FALSE),"No encontrado") -> No encontrado
A129: 2302 | B129: 1090398084 | C129: 1 | D129: LEIDY JOHANNA | E129: PEÑARANDA CONTRERAS | F129: 3118430177 | G129: johannapenaranda54@gmail.com | H129: \N | I129: \N | J129: \N | K129: 32477 | L129: \N | M129: 2 | N129: 6 | O129: \N | P129: \N | Q129: \N | R129: \N | S129: \N | T129: \N | U129: \N | V129: \N | W129: Pendiente | X129: 45936 | Y129: 0 | Z129: \N | AA129: =IFERROR(VLOOKUP(B129,BD_Clez_Premigracion!C:C,1,FALSE),"No encontrado") -> 1090398084
A130: 2176 | B130: 1005372165 | C130: 1 | D130: ANA CAMILA | E130: CAAMAÑO DIAZ | F130: 3124778011 | G130: camilacd0926@gmail.com | H130: \N | I130: Calle 8 # 11-47 | J130: 2 | K130: 37020 | L130: \N | M130: 2 | N130: 3 | O130: \N | P130: \N | Q130: \N | R130: 4 | S130: Samuel Caamaño | T130: Hermano/a | U130: 3172798847 | V130: \N | W130: Activo | X130: 45921 | Y130: 0 | AA130: =IFERROR(VLOOKUP(B130,BD_Clez_Premigracion!C:C,1,FALSE),"No encontrado") -> No encontrado
...

Sheet AfiliadosRecurrentesNuevos
A1: IdAfiliado | B1: DocumentoAfiliado | C1: idTipoDocumento | D1: NombreAfiliado | E1: ApellidoAfiliado | F1: CelularAfiliado | G1: EmailAfiliado | H1: ClaveAfiliado | I1: DireccionAfiliado | J1: idCiudadAfiliado | K1: FechaNacAfiliado | L1: FotoAfiliado | M1: idGenero | N1: idSede | O1: idEstadoCivilAfiliado | P1: idEmpresaAfil | Q1: idProfesion | R1: idEPS | S1: ResponsableAfiliado | T1: Parentesco | U1: ContactoAfiliado | V1: idUsuario | W1: EstadoAfiliado | X1: FechaAfiliacion | Y1: ProcesoActFecNac | Z1: ObservacionesParQ | AA1: idPlan
A2: 2169 | B2: 1098608981 | C2: 1 | D2: JONATHAN DAVID | E2: RODRIGUEZ CONDE | F2: 3213472473 | G2: jonathan.rodriguez2941@gmail.com | H2: \N | I2: \N | J2: 1 | K2: 38034 | L2: \N | M2: 1 | N2: 2 | O2: \N | P2: \N | Q2: \N | R2: \N | S2: \N | T2: \N | U2: \N | V2: \N | W2: Pendiente | X2: 45919 | Y2: 0 | Z2: \N | AA2: 1
A3: 2178 | B3: 1092386369 | C3: 1 | D3: EDUARDO ANDRES | E3: RAMIREZ CARDENAS | F3: 3142927674 | G3: Eduardoandres_1998@hotmail.com | H3: \N | I3: Villas de Montecarlo casa C10 | J3: \N | K3: 35985 | L3: \N | M3: 1 | N3: 4 | O3: \N | P3: \N | Q3: \N | R3: 1 | S3: Luz cardneas | T3: Padre/Madre | U3: 3124528163 | V3: \N | W3: Activo | X3: 45922 | Y3: 0 | AA3: 1
A4: 2182 | B4: 1126424740 | C4: 1 | D4: PAULO CESAR | E4: RINCON NAVARRO | F4: 3228742598 | G4: paulorinconpr88@gmail.com | H4: \N | I4: \N | J4: \N | K4: 26839 | L4: \N | M4: 1 | N4: 4 | O4: \N | P4: \N | Q4: \N | R4: \N | S4: \N | T4: \N | U4: \N | V4: \N | W4: Pendiente | X4: 45922 | Y4: 0 | Z4: \N | AA4: 1
A5: 2185 | B5: 1098766559 | C5: 1 | D5: KAREN ALICIA | E5: PABON RIATIGA | F5: 3212371879 | G5: aliciapabon1994@gmail.com | H5: \N | I5: \N | J5: \N | K5: 34669 | L5: \N | M5: 2 | N5: 8 | O5: \N | P5: \N | Q5: \N | R5: \N | S5: \N | T5: \N | U5: \N | V5: \N | W5: Pendiente | X5: 45922 | Y5: 0 | Z5: \N | AA5: 1
A6: 2197 | B6: 1095944090 | C6: 1 | D6: TATIANA ANDREA | E6: SILVA CARDENAS | F6: 3132497055 | G6: Andrea_silva31@hotmail.com | H6: \N | I6: \N | J6: \N | K6: 35216 | L6: \N | M6: 2 | N6: 8 | O6: \N | P6: \N | Q6: \N | R6: \N | S6: \N | T6: \N | U6: \N | V6: \N | W6: Pendiente | X6: 45924 | Y6: 0 | Z6: \N | AA6: 1
A7: 2217 | B7: 1007398638 | C7: 1 | D7: BEDER MOISES | E7: DURAN DUQUE | F7: 3156115465 | G7: duranbeder06@gmail.com | H7: \N | I7: \N | J7: \N | K7: 36562 | L7: \N | M7: 1 | N7: 2 | O7: \N | P7: \N | Q7: \N | R7: \N | S7: \N | T7: \N | U7: \N | V7: \N | W7: Pendiente | X7: 45926 | Y7: 0 | Z7: \N | AA7: 1
A8: 2223 | B8: 1005281651 | C8: 1 | D8: NICOLAS FELIPE | E8: MURILLO ESTEBAN | F8: 3025118581 | G8: nicolasfoxin@gmail.com | H8: \N | I8: \N | J8: \N | K8: 36865 | L8: \N | M8: 1 | N8: 2 | O8: \N | P8: \N | Q8: \N | R8: \N | S8: \N | T8: \N | U8: \N | V8: \N | W8: Pendiente | X8: 45927 | Y8: 0 | Z8: \N | AA8: 1
A9: 2232 | B9: 1098718284 | C9: 1 | D9: JORGE ANDRES | E9: BAUTISTA MENDEZ | F9: 3153049735 | G9: joanbamen23@gmail.com | H9: \N | I9: Avenida Búcaros #60-319 torocoma T4 101 | J9: \N | K9: 33657 | L9: \N | M9: 1 | N9: 10 | O9: \N | P9: \N | Q9: \N | R9: 6 | S9: Mongui Muñoz | T9: Padre/Madre | U9: 3168795456 | V9: \N | W9: Activo | X9: 45929 | Y9: 0 | AA9: 18
A10: 2234 | B10: 1098070689 | C10: 1 | D10: DANIEL HERNANDO | E10: LOPEZ VEGA | F10: 3107907445 | G10: Danielopesitos@gmail.com | H10: \N | I10: Calle 50#22-87 | J10: \N | K10: 38289 | L10: \N | M10: 1 | N10: 2 | O10: \N | P10: \N | Q10: \N | R10: 3 | S10: Hernando Lopez | T10: Padre/Madre | U10: 3212570548 | V10: \N | W10: Activo | X10: 45929 | Y10: 0 | AA10: 1
A11: 2235 | B11: 1098819918 | C11: 1 | D11: ANDRY YURANY | E11: ANDRADE SANDOVAL | F11: 3223223953 | G11: Andryur05@gmail.com | H11: \N | I11: Carrera 18#8a-30 | J11: \N | K11: 36316 | L11: \N | M11: 2 | N11: 2 | O11: \N | P11: \N | Q11: \N | R11: 1 | S11: Daniel | T11: Esposo/a | U11: 3107907445 | V11: \N | W11: Activo | X11: 45929 | Y11: 0 | AA11: 1
A12: 2236 | B12: 1044607327 | C12: 1 | D12: ISABEL SOFIA | E12: RUEDA PORRAS | F12: 3043322841 | G12: Isabelsrueda23@gmail.com | H12: \N | I12: TV 154 #157-65 | J12: \N | K12: 38344 | L12: \N | M12: 2 | N12: 3 | O12: \N | P12: \N | Q12: \N | R12: 7 | S12: Shirley porras | T12: Padre/Madre | U12: 3155130595 | V12: \N | W12: Activo | X12: 45929 | Y12: 0 | AA12: 1
A13: 2237 | B13: 1102361317 | C13: 3 | D13: Miguel Angel | E13: Torres Martinez | F13: 3006043949 | G13: miguelangeltorresmartinez07@gmail.com | H13: \N | I13: Cr 15 # 18-70 | J13: \N | K13: 39329 | L13: \N | M13: 1 | N13: 5 | O13: \N | P13: \N | Q13: \N | R13: 25 | S13: Mary luz Martínez castro | T13: Padre/Madre | U13: 3144219919 | V13: \N | W13: Activo | X13: 45929 | Y13: 0 | AA13: 1
A14: 2238 | B14: 1094267818 | C14: 1 | D14: Sair Alberto | E14: Pineda Gamboa | F14: 3016218873 | G14: sairalberto@gmail.com | H14: \N | I14: Callejas Torres | J14: \N | K14: 33565 | L14: \N | M14: 1 | N14: 4 | O14: \N | P14: \N | Q14: \N | R14: 7 | S14: Katherin Caceres | T14: Esposo/a | U14: 3168294669 | V14: \N | W14: Activo | X14: 45929 | Y14: 0 | AA14: 19
A15: 2250 | B15: 1076666956 | C15: 1 | D15: BRAYAN STIVEN | E15: RODRIGUEZ RODRIGUEZ | F15: 3204782802 | G15: brayansrodrig@gmail.com | H15: \N | I15: \N | J15: \N | K15: 35753 | L15: \N | M15: 1 | N15: 6 | O15: \N | P15: \N | Q15: \N | R15: \N | S15: \N | T15: \N | U15: \N | V15: \N | W15: Pendiente | X15: 45930 | Y15: 0 | Z15: \N | AA15: 19
A16: 2242 | B16: 1005282516 | C16: 1 | D16: ANGIE CRISTINA | E16: LOZANO MOGOLLON | F16: 3163220791 | G16: cristinangie09@gmail.com | H16: \N | I16: D | J16: \N | K16: 37873 | L16: \N | M16: 2 | N16: 3 | O16: \N | P16: \N | Q16: \N | R16: 9 | S16: Esperanza Mogollón Chaparro | T16: Padre/Madre | U16: 3152841584 | V16: \N | W16: Activo | X16: 45930 | Y16: 0 | AA16: 1
A17: 2255 | B17: 32175631 | C17: 2 | D17: Angel | E17: Guillén | F17: 3166370293 | G17: angeloguillen85@gmail.com | H17: \N | I17: \N | J17: \N | K17: 38602 | L17: \N | M17: 1 | N17: 10 | O17: \N | P17: \N | Q17: \N | R17: \N | S17: \N | T17: \N | U17: \N | V17: \N | W17: Pendiente | X17: 45930 | Y17: 0 | Z17: \N | AA17: 18
A18: 2256 | B18: 1098073585 | C18: 3 | D18: Sara | E18: Otalora bohorquez | F18: 3108897521 | G18: Otalorasara244@gmail.com | H18: \N | I18: Piedecuesta a | J18: \N | K18: 39550 | L18: \N | M18: 2 | N18: 5 | O18: \N | P18: \N | Q18: \N | R18: 7 | S18: Sonia Isabel Bohórquez Vargas | T18: Padre/Madre | U18: 3146061376 | V18: \N | W18: Activo | X18: 45930 | Y18: 0 | AA18: 1
A19: 2261 | B19: 1098625892 | C19: 1 | D19: DANIELA DAYANA | E19: RINCON DIAZ | F19: 3153740663 | G19: cr2386661@gmail.com | H19: \N | I19: \N | J19: \N | K19: 38322 | L19: \N | M19: 2 | N19: 10 | O19: \N | P19: \N | Q19: \N | R19: \N | S19: \N | T19: \N | U19: \N | V19: \N | W19: Pendiente | X19: 45930 | Y19: 0 | Z19: \N | AA19: 18
A20: 2264 | B20: 1090475652 | C20: 1 | D20: David | E20: Escobar | F20: 3022944427 | G20: qqtabox@gmail.com | H20: \N | I20: Ed Alto pamplonita 407 | J20: \N | K20: 34314 | L20: \N | M20: 1 | N20: 6 | O20: \N | P20: \N | Q20: \N | R20: 4 | S20: Myriam | T20: Padre/Madre | U20: 3164538487 | V20: \N | W20: Activo | X20: 45931 | Y20: 0 | AA20: 18
A21: 2275 | B21: 1096700440 | C21: 1 | D21: MAILETH STEFANNY | E21: HURTADO MUÑOZ | F21: 3245568323 | G21: mailethstefanny.h@gmail.com | H21: \N | I21: CRA 15#65-50 | J21: \N | K21: 38234 | L21: \N | M21: 2 | N21: 10 | O21: \N | P21: \N | Q21: \N | R21: 9 | S21: GLORIA ENIT MUÑOZ GOMEZ | T21: Padre/Madre | U21: 3142127071 | V21: \N | W21: Activo | X21: 45931 | Y21: 0 | AA21: 19
A22: 2280 | B22: 1093775147 | C22: 1 | D22: JOICY DAYANNA | E22: SAAVEDRA MEDINA | F22: 3023859906 | G22: saavedrajoicy@gmail.com | H22: \N | I22: Cll 10An # 2A-23 bosque paraiso | J22: \N | K22: 34632 | L22: \N | M22: 2 | N22: 6 | O22: \N | P22: \N | Q22: \N | R22: 5 | S22: Nancy Saavedra | T22: Padre/Madre | U22: 3142944260 | V22: \N | W22: Activo | X22: 45932 | Y22: 0 | AA22: 19
A23: 2284 | B23: 1090535263 | C23: 1 | D23: FREDDY | E23: PARADA ORTEGA | F23: 3135740397 | G23: Freddypara46@gmail.com | H23: \N | I23: \N | J23: \N | K23: 36451 | L23: \N | M23: 1 | N23: 4 | O23: \N | P23: \N | Q23: \N | R23: \N | S23: \N | T23: \N | U23: \N | V23: \N | W23: Pendiente | X23: 45932 | Y23: 0 | Z23: \N | AA23: 1
A24: 2290 | B24: 1097911303 | C24: 1 | D24: LESLY VALENTINA | E24: PINZON PALOMINO | F24: 3001632609 | G24: leslyevalentina4@gmail.com | H24: \N | I24: Calle 7N 7-53 apto 501 edificio Infinity Junín 1 | J24: \N | K24: 38768 | L24: \N | M24: 2 | N24: 5 | O24: \N | P24: \N | Q24: \N | R24: 7 | S24: DIANA CAROLINA PALOMINO | T24: Padre/Madre | U24: 3208307393 | V24: \N | W24: Activo | X24: 45933 | Y24: 0 | AA24: 1
A25: 2294 | B25: 1095934040 | C25: 1 | D25: PAOLA ANDREA | E25: SIERRA LOZANO | F25: 3106732017 | G25: Paosierralozano@gmail.com | H25: \N | I25: Calle 10 22 53 | J25: \N | K25: 34218 | L25: \N | M25: 2 | N25: 8 | O25: \N | P25: \N | Q25: \N | R25: 1 | S25: Gladys Lozano | T25: Padre/Madre | U25: 3102356844 | V25: \N | W25: Activo | X25: 45933 | Y25: 0 | AA25: 1
A26: 2295 | B26: 1005028371 | C26: 1 | D26: MICHELLE DANIELA | E26: BERMON ROMAN | F26: 3114043359 | G26: michellebermon5@gmail.com | H26: \N | I26: Mz D19 lote 13 torcoroma II | J26: \N | K26: 37762 | L26: \N | M26: 2 | N26: 4 | O26: \N | P26: \N | Q26: \N | R26: 4 | S26: Bernarda Roman | T26: Padre/Madre | U26: 3225907946 | V26: \N | W26: Activo | X26: 45933 | Y26: 0 | AA26: 1
A27: 2293 | B27: 1116798906 | C27: 1 | D27: CAMILO ALEJANDRO | E27: SANDOVAL CISNEROS | F27: 3152222034 | G27: alejandro_cisneros94@hotmail.com | H27: \N | I27: \N | J27: \N | K27: 34526 | L27: \N | M27: 1 | N27: 2 | O27: \N | P27: \N | Q27: \N | R27: \N | S27: \N | T27: \N | U27: \N | V27: \N | W27: Pendiente | X27: 45933 | Y27: 0 | Z27: \N | AA27: 1
A28: 2298 | B28: 1093590952 | C28: 1 | D28: Anthony Lizandro | E28: Blanco Villarreal | F28: 3138034366 | G28: anthonygamerz12@gmail.com | H28: \N | I28: Avenida 5B #8-30 Prados del este | J28: \N | K28: 38456 | L28: \N | M28: 1 | N28: 4 | O28: \N | P28: \N | Q28: \N | R28: 4 | S28: Joselin Andrea Villarreal | T28: Padre/Madre | U28: 3102388347 | V28: \N | W28: Activo | X28: 45935 | Y28: 0 | AA28: 19
A29: 2299 | B29: 1090393647 | C29: 1 | D29: JOSELIN ANDREA | E29: VILLARREAL | F29: 3102388347 | G29: jandreavillareal@gmail.com | H29: \N | I29: Av 5B#8-30 Prados del Este | J29: \N | K29: 32275 | L29: \N | M29: 2 | N29: 4 | O29: \N | P29: \N | Q29: \N | R29: 4 | S29: Anthony Blanco | T29: Hijo/a | U29: 3108034366 | V29: \N | W29: Activo | X29: 45935 | Y29: 0 | AA29: 19
A30: 2300 | B30: 1005051293 | C30: 1 | D30: MARIA CAMILA | E30: PARDO REALES | F30: 3133119819 | G30: Mariacamilapardo@outlook.es | H30: \N | I30: Avenida libertadores conjunto residencial prados 1 casa 18 | J30: \N | K30: 36582 | L30: \N | M30: 2 | N30: 4 | O30: \N | P30: \N | Q30: \N | R30: 4 | S30: Nathaly Orozco | T30: Primo/a | U30: +57 316 6866784 | V30: \N | W30: Activo | X30: 45935 | Y30: 0 | AA30: 18
A31: 2176 | B31: 1005372165 | C31: 1 | D31: ANA CAMILA | E31: CAAMAÑO DIAZ | F31: 3124778011 | G31: camilacd0926@gmail.com | H31: \N | I31: Calle 8 # 11-47 | J31: 2 | K31: 37020 | L31: \N | M31: 2 | N31: 3 | O31: \N | P31: \N | Q31: \N | R31: 4 | S31: Samuel Caamaño | T31: Hermano/a | U31: 3172798847 | V31: \N | W31: Activo | X31: 45921 | Y31: 0 | AA31: 1
A32: 2305 | B32: 1005106523 | C32: 1 | D32: LISETTE CARINA | E32: RODRIGUEZ MORENO | F32: 3193334006 | G32: rlisette2002@gmail.com | H32: \N | I32: Cll 64a #17a-77 | J32: \N | K32: 37401 | L32: \N | M32: 2 | N32: 10 | O32: \N | P32: \N | Q32: \N | R32: 7 | S32: Rosa moreno | T32: Padre/Madre | U32: 3153059310 | V32: \N | W32: Activo | X32: 45936 | Y32: 0 | AA32: 19
A33: 2310 | B33: 1098666487 | C33: 1 | D33: MONICA CRISTINA | E33: VELASCO ALARCON | F33: 3224670610 | G33: monicaavelascoo18@gmail.com | H33: \N | I33: CAÑAVERAL | J33: \N | K33: 32358 | L33: \N | M33: 2 | N33: 3 | O33: \N | P33: \N | Q33: \N | R33: 1 | S33: 0 | T33: Padre/Madre | U33: 311123123 | V33: \N | W33: Activo | X33: 45936 | Y33: 0 | AA33: 19
A34: 2311 | B34: 1097109207 | C34: 3 | D34: Daniel Felipe | E34: Hernández Salgado | F34: 3046481368 | G34: dh787797@gmail.com | H34: \N | I34: Villa lina | J34: \N | K34: 40379 | L34: \N | M34: 1 | N34: 5 | O34: \N | P34: \N | Q34: \N | R34: 3 | S34: July Paola | T34: Padre/Madre | U34: 3126180405 | V34: \N | W34: Activo | X34: 45936 | Y34: 0 | AA34: 1
A35: 2312 | B35: 1097912477 | C35: 3 | D35: Angel | E35: Gonzalez | F35: 3012814637 | G35: angeldavid.gonzalez0512@gmail.com | H35: \N | I35: Calle 7N#3A-82 | J35: \N | K35: 39421 | L35: \N | M35: 1 | N35: 5 | O35: \N | P35: \N | Q35: \N | R35: 7 | S35: 312438662 | T35: Padre/Madre | U35: 5700390 | V35: \N | W35: Activo | X35: 45936 | Y35: 0 | AA35: 1
A36: 2315 | B36: 1098817468 | C36: 1 | D36: SHARON DANIELA | E36: ACOSTA VILLARREAL | F36: 3006938763 | G36: SHADAAVI08@GMAIL.COM | H36: \N | I36: \N | J36: \N | K36: 36242 | L36: \N | M36: 2 | N36: 3 | O36: \N | P36: \N | Q36: \N | R36: \N | S36: \N | T36: \N | U36: \N | V36: \N | W36: Pendiente | X36: 45936 | Y36: 0 | Z36: \N | AA36: 19
A37: 2316 | B37: 1010842283 | C37: 3 | D37: Dam Sebastián | E37: Vargas Sarmiento | F37: 3228904885 | G37: damsebastianvargassarmiento@gmail.com | H37: \N | I37: Calle 0 # 5 - 21 | J37: \N | K37: 40368 | L37: \N | M37: 1 | N37: 4 | O37: \N | P37: \N | Q37: \N | R37: 4 | S37: Blanca Sarmiento | T37: Padre/Madre | U37: 3223110942 | V37: \N | W37: Activo | X37: 45936 | Y37: 0 | AA37: 1
A38: 2320 | B38: 1097490380 | C38: 1 | D38: Emmanuel | E38: Gomez | F38: 3174808163 | G38: axnel19@gmail.com | H38: \N | I38: \N | J38: \N | K38: 38367 | L38: \N | M38: 1 | N38: 2 | O38: \N | P38: \N | Q38: \N | R38: \N | S38: \N | T38: \N | U38: \N | V38: \N | W38: Pendiente | X38: 45936 | Y38: 0 | Z38: \N | AA38: 19
A39: 2321 | B39: 1005288015 | C39: 1 | D39: LADY ESTEFANIA | E39: MANTILLA MEJIA | F39: 3173016819 | G39: ladymantillamejia@gmail.com | H39: \N | I39: Carrera 16 no. 3N-09 quinta granada | J39: \N | K39: 37068 | L39: \N | M39: 2 | N39: 5 | O39: \N | P39: \N | Q39: \N | R39: 6 | S39: Sebastián Parra | T39: Esposo/a | U39: 3188942930 | V39: \N | W39: Activo | X39: 45936 | Y39: 0 | Z39: Hipoglicemia | AA39: 19
A40: 2322 | B40: 1005066160 | C40: 1 | D40: RICARDO ALEXIS | E40: PARADA BAUTISTA | F40: 3212512443 | G40: Ricardoalexispb@ufps.edu.co | H40: \N | I40: \N | J40: \N | K40: 36732 | L40: \N | M40: 1 | N40: 6 | O40: \N | P40: \N | Q40: \N | R40: \N | S40: \N | T40: \N | U40: \N | V40: \N | W40: Pendiente | X40: 45936 | Y40: 0 | Z40: \N | AA40: 18
A41: 2330 | B41: 1093592999 | C41: 1 | D41: SIMON ALEJANDRO | E41: CARDENAS TORRES | F41: 3145824033 | G41: alejoct06@gmail.com | H41: \N | I41: \N | J41: \N | K41: 38809 | L41: \N | M41: 1 | N41: 6 | O41: \N | P41: \N | Q41: \N | R41: \N | S41: \N | T41: \N | U41: \N | V41: \N | W41: Pendiente | X41: 45937 | Y41: 0 | Z41: \N | AA41: 19
A42: 2335 | B42: 7142068 | C42: 4 | D42: Jeffly Manuel | E42: Pierre Jourdain | F42: 8492817283 | G42: manuelabreu1212@protonmail.com | H42: \N | I42: Cl. 37 #24-49, Bolívar, Bucaramanga, Bolívar, Colombia | J42: \N | K42: 28300 | L42: \N | M42: 1 | N42: 2 | O42: \N | P42: \N | Q42: \N | R42: 12 | S42: Jean Reginald pierre | T42: Padre/Madre | U42: +18295409846 | V42: \N | W42: Activo | X42: 45937 | Y42: 0 | AA42: 19
A43: 2338 | B43: 1090507813 | C43: 1 | D43: Neider Juliano | E43: Medina Medina | F43: 3105879493 | G43: neidermedina1003@gmail.com | H43: \N | I43: \N | J43: \N | K43: 35601 | L43: \N | M43: 1 | N43: 8 | O43: \N | P43: \N | Q43: \N | R43: \N | S43: \N | T43: \N | U43: \N | V43: \N | W43: Pendiente | X43: 45938 | Y43: 0 | Z43: \N | AA43: 1
A44: 2345 | B44: 1090506303 | C44: 1 | D44: BRANDON STEEVEN | E44: DAZA JAIMES | F44: 3151177779 | G44: Bdajaimes@outlook.com | H44: \N | I44: \N | J44: \N | K44: 35588 | L44: \N | M44: 1 | N44: 4 | O44: \N | P44: \N | Q44: \N | R44: \N | S44: \N | T44: \N | U44: \N | V44: \N | W44: Pendiente | X44: 45939 | Y44: 0 | Z44: \N | AA44: 18
A45: 2347 | B45: 1102356101 | C45: 1 | D45: Silvia Karina | E45: Caballero Melo | F45: 3017826679 | G45: silviac202329@gmail.com | H45: \N | I45: # - Finca Villa Stella, Vereda Guariguará | J45: \N | K45: 37731 | L45: \N | M45: 2 | N45: 5 | O45: \N | P45: \N | Q45: \N | R45: 4 | S45: Enid Melo | T45: Padre/Madre | U45: 3015658878 | V45: \N | W45: Activo | X45: 45939 | Y45: 0 | AA45: 19
A46: 2348 | B46: 1005543183 | C46: 1 | D46: ARLY STEICY | E46: RAMIREZ RUEDA | F46: 3158712434 | G46: Arliramirez0326@gmail.com | H46: \N | I46: Carrera 4a#18a05 | J46: \N | K46: 36772 | L46: \N | M46: 2 | N46: 5 | O46: \N | P46: \N | Q46: \N | R46: 4 | S46: Sergio galvis | T46: Esposo/a | U46: 3178530929 | V46: \N | W46: Activo | X46: 45939 | Y46: 0 | AA46: 1
A47: 2357 | B47: 1093598744 | C47: 3 | D47: Lia Gabriela | E47: Montoya Pérez | F47: 3024278108 | G47: ligamonpe@gmail.com | H47: \N | I47: Cl. 7 Este #7-90, Urb Prados del este | J47: \N | K47: 40049 | L47: \N | M47: 2 | N47: 4 | O47: \N | P47: \N | Q47: \N | R47: 1 | S47: Carmen de Fex | T47: Tutor/a | U47: 3185997604 | V47: \N | W47: Activo | X47: 45940 | Y47: 0 | AA47: 1
A48: 2360 | B48: 1005058917 | C48: 1 | D48: ANGELICA | E48: FORERO ORTEGA | F48: 3232256477 | G48: Ytu.angelica@gmail.com | H48: \N | I48: Avenida 7#4A-53 prados del este | J48: \N | K48: 37212 | L48: \N | M48: 2 | N48: 6 | O48: \N | P48: \N | Q48: \N | R48: 1 | S48: Ana ortega | T48: Padre/Madre | U48: 3142792475 | V48: \N | W48: Activo | X48: 45940 | Y48: 0 | AA48: 18
A49: 2361 | B49: 1095965745 | C49: 1 | D49: Javier Alejandro | E49: Marquez Carmona | F49: 3228205653 | G49: javieraleja203@gmail.com | H49: \N | I49: \N | J49: \N | K49: 37687 | L49: \N | M49: 1 | N49: 2 | O49: \N | P49: \N | Q49: \N | R49: \N | S49: \N | T49: \N | U49: \N | V49: \N | W49: Pendiente | X49: 45940 | Y49: 0 | Z49: \N | AA49: 19
A50: 2369 | B50: 1099735873 | C50: 1 | D50: VALENTINA | E50: LOZADA QUINTERO | F50: 3237972096 | G50: valentinalozada.uni@gmail.com | H50: \N | I50: Cll 3BN # 0w-52 | J50: \N | K50: 38334 | L50: \N | M50: 2 | N50: 5 | O50: \N | P50: \N | Q50: \N | R50: 4 | S50: Diana Rueda | T50: Hermano/a | U50: 3238063061 | V50: \N | W50: Activo | X50: 45942 | Y50: 0 | AA50: 18
A51: 2377 | B51: 1090528973 | C51: 1 | D51: JESUS ALBERTO | E51: PUERTO CACERES | F51: 3213573438 | G51: Jpuerto0610@gmail.com | H51: \N | I51: Carrera 25 36-84 floridablanca | J51: \N | K51: 36321 | L51: \N | M51: 1 | N51: 3 | O51: \N | P51: \N | Q51: \N | R51: 1 | S51: Diego Cartagena | T51: Tutor/a | U51: 321 7554411 | V51: \N | W51: Activo | X51: 45943 | Y51: 0 | AA51: 1
A52: 2378 | B52: 1098819121 | C52: 1 | D52: Andrés Camilo | E52: Riaño | F52: 3219111149 | G52: yocamilo4@gmail.com | H52: \N | I52: carrera 29 #96-78 | J52: \N | K52: 36274 | L52: \N | M52: 1 | N52: 2 | O52: \N | P52: \N | Q52: \N | R52: 1 | S52: Saul Mauricio Riaño | T52: Padre/Madre | U52: 3006754749 | V52: \N | W52: Activo | X52: 45943 | Y52: 0 | AA52: 19
A53: 2375 | B53: 1098631699 | C53: 1 | D53: Jhonn Alexander | E53: Barajas Gómez | F53: 3155525970 | G53: jhonn_barg@hotmail.com | H53: \N | I53: Cl 9 # 16 - 29 apto 508 | J53: \N | K53: 31798 | L53: \N | M53: 1 | N53: 1 | O53: \N | P53: \N | Q53: \N | R53: 1 | S53: Jesus Barajas | T53: Padre/Madre | U53: 302 2622546 | V53: \N | W53: Activo | X53: 45943 | Y53: 0 | AA53: 19
A54: 2376 | B54: 1098765354 | C54: 1 | D54: WENDY JURANNY | E54: SUAREZ ROJAS | F54: 3235339663 | G54: yurany.suarez@outlook.com | H54: \N | I54: \N | J54: \N | K54: 34738 | L54: \N | M54: 2 | N54: 1 | O54: \N | P54: \N | Q54: \N | R54: \N | S54: \N | T54: \N | U54: \N | V54: \N | W54: Pendiente | X54: 45943 | Y54: 0 | Z54: \N | AA54: 19
A55: 2382 | B55: 1007358928 | C55: 1 | D55: SERGIO ANDRES | E55: FONSECA QUINTERO | F55: 3107276598 | G55: sergio052000@icloud.com | H55: \N | I55: Cuidad Bolivar calle 64-712 | J55: \N | K55: 36651 | L55: \N | M55: 1 | N55: 10 | O55: \N | P55: \N | Q55: \N | R55: 7 | S55: Santiago Fonseca | T55: Padre/Madre | U55: 3113168958 | V55: \N | W55: Activo | X55: 45943 | Y55: 0 | AA55: 19
A56: 2383 | B56: 1005187841 | C56: 1 | D56: NATALIA | E56: MORRIS BALLESTEROS | F56: 3157290898 | G56: nataliamorris25@hotmail.com | H56: \N | I56: \N | J56: \N | K56: 36794 | L56: \N | M56: 2 | N56: 7 | O56: \N | P56: \N | Q56: \N | R56: \N | S56: \N | T56: \N | U56: \N | V56: \N | W56: Pendiente | X56: 45944 | Y56: 0 | Z56: \N | AA56: 1
A57: 2384 | B57: 1098816087 | C57: 1 | D57: RICHARD YESHUA | E57: RUBIO RODRIGUEZ | F57: 3162364983 | G57: richardrubio6707@gmail.com | H57: \N | I57: Cra 29 #45-45 | J57: \N | K57: 36197 | L57: \N | M57: 1 | N57: 2 | O57: \N | P57: \N | Q57: \N | R57: 1 | S57: Marco Rubio | T57: Padre/Madre | U57: 3138433563 | V57: \N | W57: Activo | X57: 45944 | Y57: 0 | AA57: 18
A58: 2388 | B58: 1102726114 | C58: 1 | D58: BRAYAN DANIEL | E58: CORONELL RODRIGUEZ | F58: 3142451534 | G58: bradacoro@gmail.com | H58: \N | I58: bradacoro@gmail.com | J58: \N | K58: 36387 | L58: \N | M58: 1 | N58: 1 | O58: \N | P58: \N | Q58: \N | R58: 6 | S58: Marisol Rodriguez Mesa | T58: Padre/Madre | U58: 3102932984 | V58: \N | W58: Activo | X58: 45944 | Y58: 0 | AA58: 19
A59: 2396 | B59: 1097780926 | C59: 1 | D59: SILVIA NATHALIA | E59: ORTEGA GOMEZ | F59: 3156260158 | G59: silviaortega.ng@gmail.com | H59: \N | I59: cra23#46b-26 | J59: \N | K59: 38150 | L59: \N | M59: 2 | N59: 2 | O59: \N | P59: \N | Q59: \N | R59: 1 | S59: mayerli gomez | T59: Padre/Madre | U59: 3172937492 | V59: \N | W59: Activo | X59: 45945 | Y59: 0 | Z59: ROTURA DE LIGAMENTO CRUZADO ANTERIOR RODILLA IZQUIERDA | AA59: 19
A60: 2400 | B60: 1005051157 | C60: 1 | D60: Marian | E60: Cristancho | F60: 3202871209 | G60: mari_c.d@hotmail.com | H60: \N | I60: \N | J60: \N | K60: 36521 | L60: \N | M60: 2 | N60: 4 | O60: \N | P60: \N | Q60: \N | R60: \N | S60: \N | T60: \N | U60: \N | V60: \N | W60: Pendiente | X60: 45945 | Y60: 0 | Z60: \N | AA60: 19
A61: 2403 | B61: 1005324274 | C61: 1 | D61: UBER ANDRES | E61: MORA MONTENEGRO | F61: 3107792786 | G61: uberandresmora@gmail.com | H61: \N | I61: cll 21b #1w-21 | J61: \N | K61: 37116 | L61: \N | M61: 1 | N61: 5 | O61: \N | P61: \N | Q61: \N | R61: 3 | S61: Carlos Steven Mora Montenegro | T61: Hermano/a | U61: 3507829073 | V61: \N | W61: Activo | X61: 45945 | Y61: 0 | Z61: ninguna | AA61: 19
A62: 2404 | B62: 1096062857 | C62: 1 | D62: CARLOS STEVEN | E62: MORA MONTENEGRO | F62: 3507829073 | G62: stevenmm232@gmail.com | H62: \N | I62: cll 21b #1w-21 | J62: \N | K62: 37949 | L62: \N | M62: 1 | N62: 5 | O62: \N | P62: \N | Q62: \N | R62: 3 | S62: Uber Andres Mora Montenegro | T62: Hermano/a | U62: 3107792786 | V62: \N | W62: Activo | X62: 45945 | Y62: 0 | Z62: ninguna | AA62: 19
A63: 2387 | B63: 1097500305 | C63: 3 | D63: Alejandro | E63: Bedoya | F63: 3136468251 | G63: alejandrobedoyac26a@gmail.com | H63: \N | I63: cra 19 #8-45 | J63: \N | K63: 39766 | L63: \N | M63: 1 | N63: 1 | O63: \N | P63: \N | Q63: \N | R63: 7 | S63: Monica Cesarino | T63: Padre/Madre | U63: 3006510894 | V63: \N | W63: Activo | X63: 45944 | Y63: 0 | AA63: 19
A64: 2409 | B64: 1044621284 | C64: 1 | D64: ZHARICH ELIETH | E64: SANTRICH ZUÑIGA | F64: 3053197353 | G64: sharichzuniga581@gmail.com | H64: \N | I64: \N | J64: \N | K64: 38668 | L64: \N | M64: 2 | N64: 5 | O64: \N | P64: \N | Q64: \N | R64: \N | S64: \N | T64: \N | U64: \N | V64: \N | W64: Pendiente | X64: 45945 | Y64: 0 | Z64: \N | AA64: 1
A65: 2411 | B65: 1090470570 | C65: 1 | D65: VERONICA | E65: CASADIEGOS CELIS | F65: 3219629934 | G65: verohvm@hotmail.com | H65: \N | I65: Conjunto cerrado Riviera del este Apt 503 A | J65: \N | K65: 34320 | L65: \N | M65: 2 | N65: 4 | O65: \N | P65: \N | Q65: \N | R65: 20 | S65: Sebastián Toscano | T65: Esposo/a | U65: 3219629934 | V65: \N | W65: Activo | X65: 45945 | Y65: 0 | AA65: 19
A66: 2410 | B66: 1090510431 | C66: 1 | D66: SEBASTIAN | E66: TOSCANO TARAZONA | F66: 3011688699 | G66: Sebastoscano_15@hotmail.com | H66: \N | I66: CONJUNTO RIVIERA DEL ESTE 503A | J66: \N | K66: 35749 | L66: \N | M66: 1 | N66: 4 | O66: \N | P66: \N | Q66: \N | R66: 4 | S66: Rocio del Pilar Tarazona | T66: Padre/Madre | U66: 3134985575 | V66: \N | W66: Activo | X66: 45945 | Y66: 0 | Z66: Operado de Hernia discal y problemas por sobre peso | AA66: 19
A67: 2412 | B67: 1232889880 | C67: 1 | D67: ALEJANDRO | E67: MENDOZA HERNANDEZ | F67: 3023739241 | G67: alejandro_mendoza0620@live.com | H67: \N | I67: Cra 39 42 112 | J67: \N | K67: 35966 | L67: \N | M67: 1 | N67: 2 | O67: \N | P67: \N | Q67: \N | R67: 4 | S67: Carmen hernandez | T67: Padre/Madre | U67: 3143284782 | V67: \N | W67: Activo | X67: 45946 | Y67: 0 | AA67: 18
A68: 2413 | B68: 1099735455 | C68: 1 | D68: DANIELA | E68: ORTIZ ARENAS | F68: 3174742401 | G68: Danielaortiz125@outlook.com | H68: \N | I68: Carrera 3A #22-17 paseo del puente 2 | J68: \N | K68: 38244 | L68: \N | M68: 2 | N68: 5 | O68: \N | P68: \N | Q68: \N | R68: 4 | S68: Marlene Arenas | T68: Padre/Madre | U68: 3165369667 | V68: \N | W68: Activo | X68: 45946 | Y68: 0 | AA68: 1
A69: 2414 | B69: 1098750884 | C69: 1 | D69: DIEGO ALEXANDER | E69: JURADO TORRES | F69: 3142065133 | G69: dialexju94@gmail.com | H69: \N | I69: Cr 3w #8n 265 | J69: \N | K69: 34361 | L69: \N | M69: 1 | N69: 5 | O69: \N | P69: \N | Q69: \N | R69: 6 | S69: Giselle nathalia florez | T69: Esposo/a | U69: 3204675238 | V69: \N | W69: Activo | X69: 45946 | Y69: 0 | Z69: Sobrepeso | AA69: 1
A70: 2389 | B70: 37864385 | C70: 1 | D70: INGRID TIBISAY | E70: JEREZ MANTILLA | F70: 3208540674 | G70: ingridtibisay2113@gmail.com | H70: \N | I70: Km 4 via Pamplona | J70: \N | K70: 29911 | L70: \N | M70: 2 | N70: 8 | O70: \N | P70: \N | Q70: \N | R70: 1 | S70: Sandra Jerez Mantilla | T70: Tutor/a | U70: 3155108488 | V70: \N | W70: Activo | X70: 45944 | Y70: 0 | Z70: Asma | AA70: 18
A71: 2418 | B71: 1096062473 | C71: 1 | D71: Ricardo José | E71: Bustos becerra | F71: 3163091712 | G71: ricardojosebustosbecerra@gmail.com | H71: \N | I71: Calle 67#7-65 | J71: \N | K71: 38010 | L71: \N | M71: 1 | N71: 2 | O71: \N | P71: \N | Q71: \N | R71: 7 | S71: 3124506953 | T71: Padre/Madre | U71: 3124506953 | V71: \N | W71: Activo | X71: 45946 | Y71: 0 | AA71: 18
A72: 2421 | B72: 1090439893 | C72: 1 | D72: SONIA MILENA | E72: GALVIS ORTIZ | F72: 3046314544 | G72: milena.galvis1921@gmail.com | H72: \N | I72: Av8a # 5-86 prados del este | J72: \N | K72: 33494 | L72: \N | M72: 2 | N72: 4 | O72: \N | P72: \N | Q72: \N | R72: 4 | S72: Álvaro galvis | T72: Padre/Madre | U72: 3115283258 | V72: \N | W72: Activo | X72: 45946 | Y72: 0 | AA72: 19
A73: 2423 | B73: 63496937 | C73: 1 | D73: SANDRA MILENA | E73: DUARTE PEÑUELA | F73: 3229428955 | G73: Smduarte@keralty.co | H73: \N | I73: \N | J73: \N | K73: 27208 | L73: \N | M73: 2 | N73: 2 | O73: \N | P73: \N | Q73: \N | R73: \N | S73: \N | T73: \N | U73: \N | V73: \N | W73: Pendiente | X73: 45946 | Y73: 0 | Z73: \N | AA73: 1
A74: 2425 | B74: 1383673 | C74: 6 | D74: Anthony Jeferson | E74: Torrealba Sanchez | F74: 3114308386 | G74: anthonytjs95@gmail.com | H74: \N | I74: \N | J74: \N | K74: 34794 | L74: \N | M74: 1 | N74: 8 | O74: \N | P74: \N | Q74: \N | R74: \N | S74: \N | T74: \N | U74: \N | V74: \N | W74: Pendiente | X74: 45947 | Y74: 0 | Z74: \N | AA74: 1
A75: 2431 | B75: 1094272458 | C75: 1 | D75: Diana | E75: Villamizar | F75: 3104550094 | G75: Dianavilla.edu@gmail.com | H75: \N | I75: \N | J75: \N | K75: 34283 | L75: \N | M75: 2 | N75: 5 | O75: \N | P75: \N | Q75: \N | R75: \N | S75: \N | T75: \N | U75: \N | V75: \N | W75: Pendiente | X75: 45948 | Y75: 0 | Z75: \N | AA75: 18
A76: 2434 | B76: 1193213102 | C76: 1 | D76: LEWIS ARAMIS | E76: MANZANO GUERRERO | F76: 3184125457 | G76: lewisdev24@gmail.com | H76: \N | I76: calle 49 23 25 Poblado, Giron | J76: \N | K76: 36793 | L76: \N | M76: 1 | N76: 10 | O76: \N | P76: \N | Q76: \N | R76: 1 | S76: Mary Guerrero | T76: Padre/Madre | U76: 3223249535 | V76: \N | W76: Activo | X76: 45948 | Y76: 0 | AA76: 18
A77: 2433 | B77: 6454204 | C77: 6 | D77: Roger Ernesto | E77: Manzano | F77: 3143069558 | G77: rogercastillo0709@gmail.com | H77: \N | I77: Bucarica sector 20 | J77: \N | K77: 38967 | L77: \N | M77: 1 | N77: 3 | O77: \N | P77: \N | Q77: \N | R77: 4 | S77: Yurbay Manzano | T77: Padre/Madre | U77: 3158687878 | V77: \N | W77: Activo | X77: 45948 | Y77: 0 | AA77: 18
A78: 2439 | B78: 1098072971 | C78: 1 | D78: María José | E78: Mogollon Jiménez | F78: 3053028644 | G78: Majomoji2007@gmail.com | H78: \N | I78: Cll. 6N #4-200 conjunto Junín 2 | J78: \N | K78: 39273 | L78: \N | M78: 2 | N78: 5 | O78: \N | P78: \N | Q78: \N | R78: 4 | S78: 3105946633 | T78: Padre/Madre | U78: 3112693102 | V78: \N | W78: Activo | X78: 45950 | Y78: 0 | AA78: 1
A79: 2440 | B79: 1005290616 | C79: 1 | D79: SERGIO ANDRES | E79: DELGADO BALLESTEROS | F79: 304117355 | G79: sergio2182808@gmail.com | H79: \N | I79: calle 23 #15 - 31 | J79: \N | K79: 36997 | L79: \N | M79: 1 | N79: 10 | O79: \N | P79: \N | Q79: \N | R79: 33 | S79: Francisco Delgado | T79: Padre/Madre | U79: 3023670203 | V79: \N | W79: Activo | X79: 45950 | Y79: 0 | AA79: 1
